{
  "products": [
    {
      "id": "3802167",
      "name": "1/2 Red Riding Hood",
      "full_name": "РюЁ1/2 Red Riding Hood РџАSteam\\лалц+лњлхЛЂЛїлюлИЛђ\\KeyРГљ",
      "price": "20",
      "img": "https://graph.digiseller.ru/img.ashx?id_d=3802167&maxlength=400",
      "buy_url": "https://www.digiseller.market/asp2/pay_wm.asp?id_d=3802167&aff_id=1150998",
      "product_url": "https://www.digiseller.market/product/3802167",
      "currency": "RUB",
      "sales": "0"
    },
    {
      "id": "3782395",
      "name": "112 Operator",
      "full_name": "РюЁ112 Operator РџА Steam лџлЏл«лД лалълАлАлўл»+люлўла РГљ + ­ЪјЂ лЪлЙл┤л░ЛђлЙл║",
      "price": "139",
      "img": "https://graph.digiseller.ru/img.ashx?id_d=3782395&maxlength=400",
      "buy_url": "https://www.digiseller.market/asp2/pay_wm.asp?id_d=3782395&aff_id=1150998",
      "product_url": "https://www.digiseller.market/product/3782395",
      "currency": "RUB",
      "sales": "0"
    },
    {
      "id": "3967388",
      "name": "12 is Better Than",
      "full_name": "РюЁ12 is Better Than 6РџАSteam\\лалц+лњлхЛЂЛїлюлИЛђ\\KeyРГљ+ лџл░ЛђЛѓлЙЛЄл║лИ­ЪѓА",
      "price": "18",
      "img": "https://graph.digiseller.ru/img.ashx?id_d=3967388&maxlength=400",
      "buy_url": "https://www.digiseller.market/asp2/pay_wm.asp?id_d=3967388&aff_id=1150998",
      "product_url": "https://www.digiseller.market/product/3967388",
      "currency": "RUB",
      "sales": "0"
    },
    {
      "id": "3820829",
      "name": "Adventures of snowboarder",
      "full_name": "РюЁAdventures of a snowboarderРџАSteam\\лалц+лњлхЛЂЛїлюлИЛђ\\KeyРГљ",
      "price": "20",
      "img": "https://graph.digiseller.ru/img.ashx?id_d=3820829&maxlength=400",
      "buy_url": "https://www.digiseller.market/asp2/pay_wm.asp?id_d=3820829&aff_id=1150998",
      "product_url": "https://www.digiseller.market/product/3820829",
      "currency": "RUB",
      "sales": "0"
    },
    {
      "id": "3786542",
      "name": "Alchemy Garden",
      "full_name": "РюЁAlchemy Garden РџАSteam\\лалц+лњлхЛЂЛїлюлИЛђ\\KeyРГљ + ­ЪјЂлЉлЙлйЛЃЛЂ",
      "price": "75",
      "img": "https://graph.digiseller.ru/img.ashx?id_d=3786542&maxlength=400",
      "buy_url": "https://www.digiseller.market/asp2/pay_wm.asp?id_d=3786542&aff_id=1150998",
      "product_url": "https://www.digiseller.market/product/3786542",
      "currency": "RUB",
      "sales": "0"
    },
    {
      "id": "3935288",
      "name": "Alfonzo's Arctic Adventure",
      "full_name": "РюЁAlfonzo's Arctic AdventureРџАSteam\\лалц+лњлхЛЂЛїлюлИЛђ\\KeyРГљ + ­ЪјЂ",
      "price": "99",
      "img": "https://graph.digiseller.ru/img.ashx?id_d=3935288&maxlength=400",
      "buy_url": "https://www.digiseller.market/asp2/pay_wm.asp?id_d=3935288&aff_id=1150998",
      "product_url": "https://www.digiseller.market/product/3935288",
      "currency": "RUB",
      "sales": "0"
    },
    {
      "id": "4438322",
      "name": "Amanda The Adventurer",
      "full_name": "РюЁAmanda The Adventurer РџА Steam\\лалц+лњлхЛЂЛї люлИЛђ\\KeyРГљ + ­ЪјЂ",
      "price": "75",
      "img": "https://graph.digiseller.ru/img.ashx?id_d=4438322&maxlength=400",
      "buy_url": "https://www.digiseller.market/asp2/pay_wm.asp?id_d=4438322&aff_id=1150998",
      "product_url": "https://www.digiseller.market/product/4438322",
      "currency": "RUB",
      "sales": "0"
    },
    {
      "id": "3949760",
      "name": "Ancient Enemy",
      "full_name": "РюЁAncient EnemyРџАSteam\\лалц+лњлхЛЂЛї люлИЛђ\\KeyРГљ",
      "price": "85",
      "img": "https://graph.digiseller.ru/img.ashx?id_d=3949760&maxlength=400",
      "buy_url": "https://www.digiseller.market/asp2/pay_wm.asp?id_d=3949760&aff_id=1150998",
      "product_url": "https://www.digiseller.market/product/3949760",
      "currency": "RUB",
      "sales": "0"
    },
    {
      "id": "3916404",
      "name": "Autocraft",
      "full_name": "РюЁAutocraftРџАSteam\\лалц+лњлхЛЂЛїлюлИЛђ\\KeyРГљ",
      "price": "15",
      "img": "https://graph.digiseller.ru/img.ashx?id_d=3916404&maxlength=400",
      "buy_url": "https://www.digiseller.market/asp2/pay_wm.asp?id_d=3916404&aff_id=1150998",
      "product_url": "https://www.digiseller.market/product/3916404",
      "currency": "RUB",
      "sales": "0"
    },
    {
      "id": "3975308",
      "name": "Automatic war",
      "full_name": "РюЁAutomatic warРџАSteam\\лалц+лњлхЛЂЛї люлИЛђ\\KeyРГљ",
      "price": "149",
      "img": "https://graph.digiseller.ru/img.ashx?id_d=3975308&maxlength=400",
      "buy_url": "https://www.digiseller.market/asp2/pay_wm.asp?id_d=3975308&aff_id=1150998",
      "product_url": "https://www.digiseller.market/product/3975308",
      "currency": "RUB",
      "sales": "0"
    },
    {
      "id": "3963701",
      "name": "Autumn Hike",
      "full_name": "РюЁAutumn HikeРџАSteam\\лалц + лњлхЛЂЛї люлИЛђ\\KeyРГљ",
      "price": "135",
      "img": "https://graph.digiseller.ru/img.ashx?id_d=3963701&maxlength=400",
      "buy_url": "https://www.digiseller.market/asp2/pay_wm.asp?id_d=3963701&aff_id=1150998",
      "product_url": "https://www.digiseller.market/product/3963701",
      "currency": "RUB",
      "sales": "0"
    },
    {
      "id": "3782808",
      "name": "Autumn",
      "full_name": "РюЁAutumnРџАSteam\\лалц+лњлхЛЂЛї люлИЛђ\\KeyРГљ+ лџл░ЛђЛѓлЙЛЄл║лИ­ЪѓА",
      "price": "14",
      "img": "https://graph.digiseller.ru/img.ashx?id_d=3782808&maxlength=400",
      "buy_url": "https://www.digiseller.market/asp2/pay_wm.asp?id_d=3782808&aff_id=1150998",
      "product_url": "https://www.digiseller.market/product/3782808",
      "currency": "RUB",
      "sales": "0"
    },
    {
      "id": "3820834",
      "name": "Be King",
      "full_name": "РюЁBe KingРџАSteam\\лалц+лњлхЛЂЛїлюлИЛђ\\KeyРГљ",
      "price": "15",
      "img": "https://graph.digiseller.ru/img.ashx?id_d=3820834&maxlength=400",
      "buy_url": "https://www.digiseller.market/asp2/pay_wm.asp?id_d=3820834&aff_id=1150998",
      "product_url": "https://www.digiseller.market/product/3820834",
      "currency": "RUB",
      "sales": "0"
    },
    {
      "id": "3783223",
      "name": "Beholder",
      "full_name": "Beholder - Blissful Sleep РџАDLC Steam лалълАлАлўл»+люлўла лџлЏл«лДРГљ + ­ЪјЂ лЪлЙл┤л░ЛђлЙл║",
      "price": "39",
      "img": "https://graph.digiseller.ru/img.ashx?id_d=3783223&maxlength=400",
      "buy_url": "https://www.digiseller.market/asp2/pay_wm.asp?id_d=3783223&aff_id=1150998",
      "product_url": "https://www.digiseller.market/product/3783223",
      "currency": "RUB",
      "sales": "0"
    },
    {
      "id": "3795130",
      "name": "Best Pearl",
      "full_name": "РюЁBest PearlРџАSteam\\лалц+лњлхЛЂЛїлюлИЛђ\\KeyРГљ",
      "price": "15",
      "img": "https://graph.digiseller.ru/img.ashx?id_d=3795130&maxlength=400",
      "buy_url": "https://www.digiseller.market/asp2/pay_wm.asp?id_d=3795130&aff_id=1150998",
      "product_url": "https://www.digiseller.market/product/3795130",
      "currency": "RUB",
      "sales": "0"
    },
    {
      "id": "3815918",
      "name": "Beyond the Long Night",
      "full_name": "Beyond the Long Night РџА Steam лалц+лАлЮлЊ лџлЏл«лДРГљ + ­ЪјЂ лЪлЙл┤л░ЛђлЙл║",
      "price": "99",
      "img": "https://graph.digiseller.ru/img.ashx?id_d=3815918&maxlength=400",
      "buy_url": "https://www.digiseller.market/asp2/pay_wm.asp?id_d=3815918&aff_id=1150998",
      "product_url": "https://www.digiseller.market/product/3815918",
      "currency": "RUB",
      "sales": "0"
    },
    {
      "id": "4883958",
      "name": "Biped Screaming Chicken",
      "full_name": "РюЁBiped + Screaming ChickenРџАSteam\\лалц\\KeyРГљ + ­ЪјЂ",
      "price": "230",
      "img": "https://graph.digiseller.ru/img.ashx?id_d=4883958&maxlength=400",
      "buy_url": "https://www.digiseller.market/asp2/pay_wm.asp?id_d=4883958&aff_id=1150998",
      "product_url": "https://www.digiseller.market/product/4883958",
      "currency": "RUB",
      "sales": "0"
    },
    {
      "id": "3781476",
      "name": "Biped",
      "full_name": "РюЁBiped РџАSteam (лалЙЛЂЛЂлИЛЈ) | (лњлхЛЂЛї люлИЛђ)  лџл╗ЛјЛЄ РГљ + ­ЪјЂ лЪлЙл┤л░ЛђлЙл║",
      "price": "60",
      "img": "https://graph.digiseller.ru/img.ashx?id_d=3781476&maxlength=400",
      "buy_url": "https://www.digiseller.market/asp2/pay_wm.asp?id_d=3781476&aff_id=1150998",
      "product_url": "https://www.digiseller.market/product/3781476",
      "currency": "RUB",
      "sales": "0"
    },
    {
      "id": "3783290",
      "name": "Black Desert Online Traveler Edition Penguin лџлълћ EU/NA",
      "full_name": "Black Desert Online Traveler Edition & Penguin лџлълћ EU/NA",
      "price": "249",
      "img": "https://graph.digiseller.ru/img.ashx?id_d=3783290&maxlength=400",
      "buy_url": "https://www.digiseller.market/asp2/pay_wm.asp?id_d=3783290&aff_id=1150998",
      "product_url": "https://www.digiseller.market/product/3783290",
      "currency": "RUB",
      "sales": "0"
    },
    {
      "id": "3802171",
      "name": "Blue Sky",
      "full_name": "РюЁBlue Sky РџАSteam\\лалц+лњлхЛЂЛїлюлИЛђ\\KeyРГљ",
      "price": "15",
      "img": "https://graph.digiseller.ru/img.ashx?id_d=3802171&maxlength=400",
      "buy_url": "https://www.digiseller.market/asp2/pay_wm.asp?id_d=3802171&aff_id=1150998",
      "product_url": "https://www.digiseller.market/product/3802171",
      "currency": "RUB",
      "sales": "0"
    },
    {
      "id": "3890886",
      "name": "Bogatyr",
      "full_name": "РюЁBogatyrРџАSteam\\лалц+лњлхЛЂЛїлюлИЛђ\\KeyРГљ",
      "price": "45",
      "img": "https://graph.digiseller.ru/img.ashx?id_d=3890886&maxlength=400",
      "buy_url": "https://www.digiseller.market/asp2/pay_wm.asp?id_d=3890886&aff_id=1150998",
      "product_url": "https://www.digiseller.market/product/3890886",
      "currency": "RUB",
      "sales": "0"
    },
    {
      "id": "4841837",
      "name": "Boxes",
      "full_name": "РюЁBoxes: Lost Fragments РџАSteam\\лалц+люлИЛђ\\KeyРГљ + ­ЪјЂ лЉлЙлйЛЃЛЂ",
      "price": "79",
      "img": "https://graph.digiseller.ru/img.ashx?id_d=4841837&maxlength=400",
      "buy_url": "https://www.digiseller.market/asp2/pay_wm.asp?id_d=4841837&aff_id=1150998",
      "product_url": "https://www.digiseller.market/product/4841837",
      "currency": "RUB",
      "sales": "0"
    },
    {
      "id": "3939441",
      "name": "Broken Hearts Island",
      "full_name": "РюЁBroken Hearts IslandРџАSteam\\лалц+лњлхЛЂЛїлюлИЛђ\\KeyРГљ",
      "price": "20",
      "img": "https://graph.digiseller.ru/img.ashx?id_d=3939441&maxlength=400",
      "buy_url": "https://www.digiseller.market/asp2/pay_wm.asp?id_d=3939441&aff_id=1150998",
      "product_url": "https://www.digiseller.market/product/3939441",
      "currency": "RUB",
      "sales": "0"
    },
    {
      "id": "3916405",
      "name": "Burst Squad",
      "full_name": "РюЁBurst SquadРџАSteam\\лалц+лњлхЛЂЛїлюлИЛђ\\KeyРГљ",
      "price": "12",
      "img": "https://graph.digiseller.ru/img.ashx?id_d=3916405&maxlength=400",
      "buy_url": "https://www.digiseller.market/asp2/pay_wm.asp?id_d=3916405&aff_id=1150998",
      "product_url": "https://www.digiseller.market/product/3916405",
      "currency": "RUB",
      "sales": "0"
    },
    {
      "id": "3923792",
      "name": "Candy Smash VR",
      "full_name": "РюЁCandy Smash VRРџАSteam\\лалц+лњлхЛЂЛїлюлИЛђ\\KeyРГљ+ лџл░ЛђЛѓлЙЛЄл║лИ­ЪѓА",
      "price": "15",
      "img": "https://graph.digiseller.ru/img.ashx?id_d=3923792&maxlength=400",
      "buy_url": "https://www.digiseller.market/asp2/pay_wm.asp?id_d=3923792&aff_id=1150998",
      "product_url": "https://www.digiseller.market/product/3923792",
      "currency": "RUB",
      "sales": "0"
    },
    {
      "id": "3890925",
      "name": "Chenso Club",
      "full_name": "РюЁChenso Club РџА Steam лалълАлАлўл»+люлўла лџлЏл«лДРГљ + ­ЪјЂ лЪлЙл┤л░ЛђлЙл║",
      "price": "59",
      "img": "https://graph.digiseller.ru/img.ashx?id_d=3890925&maxlength=400",
      "buy_url": "https://www.digiseller.market/asp2/pay_wm.asp?id_d=3890925&aff_id=1150998",
      "product_url": "https://www.digiseller.market/product/3890925",
      "currency": "RUB",
      "sales": "0"
    },
    {
      "id": "3916399",
      "name": "Chris",
      "full_name": "РюЁChris - The Element RunnerРџАSteam\\лалц+лњлхЛЂЛїлюлИЛђ\\KeyРГљ",
      "price": "15",
      "img": "https://graph.digiseller.ru/img.ashx?id_d=3916399&maxlength=400",
      "buy_url": "https://www.digiseller.market/asp2/pay_wm.asp?id_d=3916399&aff_id=1150998",
      "product_url": "https://www.digiseller.market/product/3916399",
      "currency": "RUB",
      "sales": "0"
    },
    {
      "id": "3853376",
      "name": "City of Beats",
      "full_name": "РюЁCity of BeatsРџА Steam лалц+лњлхЛЂЛї люлИЛђ KeyРГљ + ­ЪјЂлЉлЙлйЛЃЛЂ",
      "price": "79",
      "img": "https://graph.digiseller.ru/img.ashx?id_d=3853376&maxlength=400",
      "buy_url": "https://www.digiseller.market/asp2/pay_wm.asp?id_d=3853376&aff_id=1150998",
      "product_url": "https://www.digiseller.market/product/3853376",
      "currency": "RUB",
      "sales": "0"
    },
    {
      "id": "3782802",
      "name": "City Siege",
      "full_name": "РюЁCity Siege: Faction IslandРџАSteam\\люлИЛђ\\KeyРГљ+ лџл░ЛђЛѓлЙЛЄл║лИ",
      "price": "13",
      "img": "https://graph.digiseller.ru/img.ashx?id_d=3782802&maxlength=400",
      "buy_url": "https://www.digiseller.market/asp2/pay_wm.asp?id_d=3782802&aff_id=1150998",
      "product_url": "https://www.digiseller.market/product/3782802",
      "currency": "RUB",
      "sales": "0"
    },
    {
      "id": "3939417",
      "name": "Clan monsters",
      "full_name": "РюЁClan monstersРџАSteam\\лалц+лњлхЛЂЛїлюлИЛђ\\KeyРГљ",
      "price": "30",
      "img": "https://graph.digiseller.ru/img.ashx?id_d=3939417&maxlength=400",
      "buy_url": "https://www.digiseller.market/asp2/pay_wm.asp?id_d=3939417&aff_id=1150998",
      "product_url": "https://www.digiseller.market/product/3939417",
      "currency": "RUB",
      "sales": "0"
    },
    {
      "id": "3820828",
      "name": "Clicker",
      "full_name": "РюЁClicker: Glad ValakasРџАSteam\\лалц+лњлхЛЂЛїлюлИЛђ\\KeyРГљ",
      "price": "29",
      "img": "https://graph.digiseller.ru/img.ashx?id_d=3820828&maxlength=400",
      "buy_url": "https://www.digiseller.market/asp2/pay_wm.asp?id_d=3820828&aff_id=1150998",
      "product_url": "https://www.digiseller.market/product/3820828",
      "currency": "RUB",
      "sales": "0"
    },
    {
      "id": "3795126",
      "name": "Cold Blooded Cube",
      "full_name": "РюЁCold Blooded CubeРџАSteam\\лалц+лњлхЛЂЛїлюлИЛђ\\KeyРГљ + лџл░ЛђЛѓлЙЛЄл║лИ­ЪѓА",
      "price": "199",
      "img": "https://graph.digiseller.ru/img.ashx?id_d=3795126&maxlength=400",
      "buy_url": "https://www.digiseller.market/asp2/pay_wm.asp?id_d=3795126&aff_id=1150998",
      "product_url": "https://www.digiseller.market/product/3795126",
      "currency": "RUB",
      "sales": "0"
    },
    {
      "id": "3977909",
      "name": "Countdown Timer",
      "full_name": "РюЁCountdown TimerРџАSteam\\лалц+лњлхЛЂЛї люлИЛђ\\KeyРГљ",
      "price": "15",
      "img": "https://graph.digiseller.ru/img.ashx?id_d=3977909&maxlength=400",
      "buy_url": "https://www.digiseller.market/asp2/pay_wm.asp?id_d=3977909&aff_id=1150998",
      "product_url": "https://www.digiseller.market/product/3977909",
      "currency": "RUB",
      "sales": "0"
    },
    {
      "id": "5619452",
      "name": "Crewsaders",
      "full_name": "Crewsaders РџАSteam лџлЏл«лД лалЙЛЂЛЂлИЛЈ+люлИЛђРГљ",
      "price": "10",
      "img": "https://graph.digiseller.ru/img.ashx?id_d=5619452&maxlength=400",
      "buy_url": "https://www.digiseller.market/asp2/pay_wm.asp?id_d=5619452&aff_id=1150998",
      "product_url": "https://www.digiseller.market/product/5619452",
      "currency": "RUB",
      "sales": "0"
    },
    {
      "id": "3913226",
      "name": "РюЁCrumbleРџАSteam\\лалц+лњлхЛЂЛїлюлИЛђ\\KeyРГљ + ­ЪјЂлЉлЙлйЛЃЛЂ",
      "full_name": "РюЁCrumbleРџАSteam\\лалц+лњлхЛЂЛїлюлИЛђ\\KeyРГљ + ­ЪјЂлЉлЙлйЛЃЛЂ",
      "price": "85",
      "img": "https://graph.digiseller.ru/img.ashx?id_d=3913226&maxlength=400",
      "buy_url": "https://www.digiseller.market/asp2/pay_wm.asp?id_d=3913226&aff_id=1150998",
      "product_url": "https://www.digiseller.market/product/3913226",
      "currency": "RUB",
      "sales": "0"
    },
    {
      "id": "4873388",
      "name": "Dead by Daylight",
      "full_name": "РюЁDead by Daylight - The Bloodstained SackРџАSteam\\Key+­ЪјЂ",
      "price": "1999",
      "img": "https://graph.digiseller.ru/img.ashx?id_d=4873388&maxlength=400",
      "buy_url": "https://www.digiseller.market/asp2/pay_wm.asp?id_d=4873388&aff_id=1150998",
      "product_url": "https://www.digiseller.market/product/4873388",
      "currency": "RUB",
      "sales": "0"
    },
    {
      "id": "3939406",
      "name": "Deadblast",
      "full_name": "РюЁDeadblastРџАSteam\\лалц+лњлхЛЂЛїлюлИЛђ\\KeyРГљ",
      "price": "25",
      "img": "https://graph.digiseller.ru/img.ashx?id_d=3939406&maxlength=400",
      "buy_url": "https://www.digiseller.market/asp2/pay_wm.asp?id_d=3939406&aff_id=1150998",
      "product_url": "https://www.digiseller.market/product/3939406",
      "currency": "RUB",
      "sales": "0"
    },
    {
      "id": "3829519",
      "name": "Deathtrap",
      "full_name": "РюЁDeathtrap РџАSteam\\лалц+лњлхЛЂЛїлюлИЛђ\\KeyРГљ + ­ЪјЂлЉлЙлйЛЃЛЂ",
      "price": "99",
      "img": "https://graph.digiseller.ru/img.ashx?id_d=3829519&maxlength=400",
      "buy_url": "https://www.digiseller.market/asp2/pay_wm.asp?id_d=3829519&aff_id=1150998",
      "product_url": "https://www.digiseller.market/product/3829519",
      "currency": "RUB",
      "sales": "0"
    },
    {
      "id": "3962858",
      "name": "Deceive Inc.",
      "full_name": "РюЁDeceive Inc.РџАSteam лалълАлАлўл»+люлИЛђ лџлЏл«лДРГљ + ­ЪјЂлЉлЙлйЛЃЛЂ",
      "price": "499",
      "img": "https://graph.digiseller.ru/img.ashx?id_d=3962858&maxlength=400",
      "buy_url": "https://www.digiseller.market/asp2/pay_wm.asp?id_d=3962858&aff_id=1150998",
      "product_url": "https://www.digiseller.market/product/3962858",
      "currency": "RUB",
      "sales": "0"
    },
    {
      "id": "3858339",
      "name": "Deep Space Battle Simulator",
      "full_name": "РюЁDeep Space Battle SimulatorРџАSteam\\лалц+лњлхЛЂЛїлюлИЛђ\\KeyРГљ + ­ЪјЂ",
      "price": "95",
      "img": "https://graph.digiseller.ru/img.ashx?id_d=3858339&maxlength=400",
      "buy_url": "https://www.digiseller.market/asp2/pay_wm.asp?id_d=3858339&aff_id=1150998",
      "product_url": "https://www.digiseller.market/product/3858339",
      "currency": "RUB",
      "sales": "0"
    },
    {
      "id": "3966723",
      "name": "Deep Space Shooter",
      "full_name": "РюЁDeep Space ShooterРџАSteam\\лалц+лњлхЛЂЛї люлИЛђ\\KeyРГљ",
      "price": "15",
      "img": "https://graph.digiseller.ru/img.ashx?id_d=3966723&maxlength=400",
      "buy_url": "https://www.digiseller.market/asp2/pay_wm.asp?id_d=3966723&aff_id=1150998",
      "product_url": "https://www.digiseller.market/product/3966723",
      "currency": "RUB",
      "sales": "0"
    },
    {
      "id": "3946144",
      "name": "Desktop Beach Girls",
      "full_name": "РюЁDesktop Beach GirlsРџАSteam\\лалц+лњлхЛЂЛїлюлИЛђ\\KeyРГљ",
      "price": "20",
      "img": "https://graph.digiseller.ru/img.ashx?id_d=3946144&maxlength=400",
      "buy_url": "https://www.digiseller.market/asp2/pay_wm.asp?id_d=3946144&aff_id=1150998",
      "product_url": "https://www.digiseller.market/product/3946144",
      "currency": "RUB",
      "sales": "0"
    },
    {
      "id": "3949766",
      "name": "Destropolis",
      "full_name": "РюЁDestropolisРџАSteam\\лалц+лњлхЛЂЛї люлИЛђ\\KeyРГљ",
      "price": "39",
      "img": "https://graph.digiseller.ru/img.ashx?id_d=3949766&maxlength=400",
      "buy_url": "https://www.digiseller.market/asp2/pay_wm.asp?id_d=3949766&aff_id=1150998",
      "product_url": "https://www.digiseller.market/product/3949766",
      "currency": "RUB",
      "sales": "0"
    },
    {
      "id": "3949763",
      "name": "Dinobot and Tiara Present",
      "full_name": "РюЁDinobot and Tiara Present: ApplePopРџАSteam\\лалц+люлИЛђ\\KeyРГљ",
      "price": "25",
      "img": "https://graph.digiseller.ru/img.ashx?id_d=3949763&maxlength=400",
      "buy_url": "https://www.digiseller.market/asp2/pay_wm.asp?id_d=3949763&aff_id=1150998",
      "product_url": "https://www.digiseller.market/product/3949763",
      "currency": "RUB",
      "sales": "0"
    },
    {
      "id": "3839373",
      "name": "Dishonored",
      "full_name": "РюЁDishonored: Death of the OutsiderРџАSteam\\лалц+люлИЛђ\\Key+­ЪјЂ",
      "price": "1049",
      "img": "https://graph.digiseller.ru/img.ashx?id_d=3839373&maxlength=400",
      "buy_url": "https://www.digiseller.market/asp2/pay_wm.asp?id_d=3839373&aff_id=1150998",
      "product_url": "https://www.digiseller.market/product/3839373",
      "currency": "RUB",
      "sales": "0"
    },
    {
      "id": "3993263",
      "name": "dot TANKI",
      "full_name": "РюЁdot TANKIРџАSteam\\лалц+лњлхЛЂЛї люлИЛђ\\KeyРГљ",
      "price": "20",
      "img": "https://graph.digiseller.ru/img.ashx?id_d=3993263&maxlength=400",
      "buy_url": "https://www.digiseller.market/asp2/pay_wm.asp?id_d=3993263&aff_id=1150998",
      "product_url": "https://www.digiseller.market/product/3993263",
      "currency": "RUB",
      "sales": "0"
    },
    {
      "id": "3946086",
      "name": "Dr Professor Scientist's Weapons Testing Facility",
      "full_name": "РюЁDr Professor Scientist's Weapons Testing Facility РџАKey",
      "price": "25",
      "img": "https://graph.digiseller.ru/img.ashx?id_d=3946086&maxlength=400",
      "buy_url": "https://www.digiseller.market/asp2/pay_wm.asp?id_d=3946086&aff_id=1150998",
      "product_url": "https://www.digiseller.market/product/3946086",
      "currency": "RUB",
      "sales": "0"
    },
    {
      "id": "3956546",
      "name": "Dungeon Rebound",
      "full_name": "РюЁDungeon ReboundРџАSteam\\лалц+лњлхЛЂЛї люлИЛђ\\KeyРГљ",
      "price": "39",
      "img": "https://graph.digiseller.ru/img.ashx?id_d=3956546&maxlength=400",
      "buy_url": "https://www.digiseller.market/asp2/pay_wm.asp?id_d=3956546&aff_id=1150998",
      "product_url": "https://www.digiseller.market/product/3956546",
      "currency": "RUB",
      "sales": "0"
    },
    {
      "id": "3890875",
      "name": "Dungeons Cocks",
      "full_name": "РюЁDungeons & CocksРџАSteam\\лалц+лњлхЛЂЛїлюлИЛђ\\KeyРГљ",
      "price": "39",
      "img": "https://graph.digiseller.ru/img.ashx?id_d=3890875&maxlength=400",
      "buy_url": "https://www.digiseller.market/asp2/pay_wm.asp?id_d=3890875&aff_id=1150998",
      "product_url": "https://www.digiseller.market/product/3890875",
      "currency": "RUB",
      "sales": "0"
    },
    {
      "id": "3782778",
      "name": "Dungeons and Myths",
      "full_name": "РюЁDungeons and Myths 2РџАSteam\\лалц+лњлхЛЂЛї люлИЛђ\\KeyРГљ",
      "price": "149",
      "img": "https://graph.digiseller.ru/img.ashx?id_d=3782778&maxlength=400",
      "buy_url": "https://www.digiseller.market/asp2/pay_wm.asp?id_d=3782778&aff_id=1150998",
      "product_url": "https://www.digiseller.market/product/3782778",
      "currency": "RUB",
      "sales": "0"
    },
    {
      "id": "3956567",
      "name": "Dungeons and Myths",
      "full_name": "РюЁDungeons and MythsРџАSteam\\лалц+лњлхЛЂЛї люлИЛђ\\KeyРГљ",
      "price": "149",
      "img": "https://graph.digiseller.ru/img.ashx?id_d=3956567&maxlength=400",
      "buy_url": "https://www.digiseller.market/asp2/pay_wm.asp?id_d=3956567&aff_id=1150998",
      "product_url": "https://www.digiseller.market/product/3956567",
      "currency": "RUB",
      "sales": "0"
    },
    {
      "id": "3956542",
      "name": "Dynaforce",
      "full_name": "РюЁDynaforceРџАSteam\\лалц+лњлхЛЂЛї люлИЛђ\\KeyРГљ",
      "price": "49",
      "img": "https://graph.digiseller.ru/img.ashx?id_d=3956542&maxlength=400",
      "buy_url": "https://www.digiseller.market/asp2/pay_wm.asp?id_d=3956542&aff_id=1150998",
      "product_url": "https://www.digiseller.market/product/3956542",
      "currency": "RUB",
      "sales": "0"
    },
    {
      "id": "3963732",
      "name": "Elysium Restaurant",
      "full_name": "РюЁElysium RestaurantРџАSteam\\лалц+лњлхЛЂЛї люлИЛђ\\KeyРГљ",
      "price": "150",
      "img": "https://graph.digiseller.ru/img.ashx?id_d=3963732&maxlength=400",
      "buy_url": "https://www.digiseller.market/asp2/pay_wm.asp?id_d=3963732&aff_id=1150998",
      "product_url": "https://www.digiseller.market/product/3963732",
      "currency": "RUB",
      "sales": "0"
    },
    {
      "id": "3946140",
      "name": "Escape From",
      "full_name": "РюЁEscape From Russia: MobilizationРџАSteam\\лалц+лњлхЛЂЛїлюлИЛђ\\KeyРГљ",
      "price": "20",
      "img": "https://graph.digiseller.ru/img.ashx?id_d=3946140&maxlength=400",
      "buy_url": "https://www.digiseller.market/asp2/pay_wm.asp?id_d=3946140&aff_id=1150998",
      "product_url": "https://www.digiseller.market/product/3946140",
      "currency": "RUB",
      "sales": "0"
    },
    {
      "id": "3946152",
      "name": "Escape From",
      "full_name": "РюЁEscape From RussiaРџАSteam\\лалц+лњлхЛЂЛїлюлИЛђ\\KeyРГљ",
      "price": "100",
      "img": "https://graph.digiseller.ru/img.ashx?id_d=3946152&maxlength=400",
      "buy_url": "https://www.digiseller.market/asp2/pay_wm.asp?id_d=3946152&aff_id=1150998",
      "product_url": "https://www.digiseller.market/product/3946152",
      "currency": "RUB",
      "sales": "0"
    },
    {
      "id": "3820823",
      "name": "Escape the City",
      "full_name": "РюЁEscape the CityРџАSteam\\лалц+лњлхЛЂЛїлюлИЛђ\\KeyРГљ",
      "price": "15",
      "img": "https://graph.digiseller.ru/img.ashx?id_d=3820823&maxlength=400",
      "buy_url": "https://www.digiseller.market/asp2/pay_wm.asp?id_d=3820823&aff_id=1150998",
      "product_url": "https://www.digiseller.market/product/3820823",
      "currency": "RUB",
      "sales": "0"
    },
    {
      "id": "3935295",
      "name": "Eskimo Bob",
      "full_name": "РюЁEskimo Bob: Starring AlfonzoРџАSteam\\лалц+лњлхЛЂЛїлюлИЛђ\\KeyРГљ+ ­ЪјЂ",
      "price": "99",
      "img": "https://graph.digiseller.ru/img.ashx?id_d=3935295&maxlength=400",
      "buy_url": "https://www.digiseller.market/asp2/pay_wm.asp?id_d=3935295&aff_id=1150998",
      "product_url": "https://www.digiseller.market/product/3935295",
      "currency": "RUB",
      "sales": "0"
    },
    {
      "id": "3939512",
      "name": "Eternal Fidelity",
      "full_name": "РюЁEternal FidelityРџАSteam\\лалц+лњлхЛЂЛїлюлИЛђ\\KeyРГљ",
      "price": "25",
      "img": "https://graph.digiseller.ru/img.ashx?id_d=3939512&maxlength=400",
      "buy_url": "https://www.digiseller.market/asp2/pay_wm.asp?id_d=3939512&aff_id=1150998",
      "product_url": "https://www.digiseller.market/product/3939512",
      "currency": "RUB",
      "sales": "0"
    },
    {
      "id": "3939453",
      "name": "Evolve Stage",
      "full_name": "РюЁEvolve Stage 2 РџАSteam\\лалц+лњлхЛЂЛїлюлИЛђ\\KeyРГљ + ­ЪјЂ",
      "price": "6289",
      "img": "https://graph.digiseller.ru/img.ashx?id_d=3939453&maxlength=400",
      "buy_url": "https://www.digiseller.market/asp2/pay_wm.asp?id_d=3939453&aff_id=1150998",
      "product_url": "https://www.digiseller.market/product/3939453",
      "currency": "RUB",
      "sales": "0"
    },
    {
      "id": "3963751",
      "name": "Fantasy Mahjong connect",
      "full_name": "РюЁFantasy Mahjong connectРџАSteam\\лалц+лњлхЛЂЛї люлИЛђ\\KeyРГљ",
      "price": "149",
      "img": "https://graph.digiseller.ru/img.ashx?id_d=3963751&maxlength=400",
      "buy_url": "https://www.digiseller.market/asp2/pay_wm.asp?id_d=3963751&aff_id=1150998",
      "product_url": "https://www.digiseller.market/product/3963751",
      "currency": "RUB",
      "sales": "0"
    },
    {
      "id": "3882687",
      "name": "Fap Simulator 2020",
      "full_name": "РюЁFap Simulator 2020РџАSteam\\лалц+лњлхЛЂЛїлюлИЛђ\\KeyРГљ",
      "price": "10",
      "img": "https://graph.digiseller.ru/img.ashx?id_d=3882687&maxlength=400",
      "buy_url": "https://www.digiseller.market/asp2/pay_wm.asp?id_d=3882687&aff_id=1150998",
      "product_url": "https://www.digiseller.market/product/3882687",
      "currency": "RUB",
      "sales": "0"
    },
    {
      "id": "3801990",
      "name": "Fears of Glasses o-o World War",
      "full_name": "РюЁFears of Glasses o-o World WarРџАSteam\\лалц+лњлхЛЂЛїлюлИЛђ\\KeyРГљ",
      "price": "45",
      "img": "https://graph.digiseller.ru/img.ashx?id_d=3801990&maxlength=400",
      "buy_url": "https://www.digiseller.market/asp2/pay_wm.asp?id_d=3801990&aff_id=1150998",
      "product_url": "https://www.digiseller.market/product/3801990",
      "currency": "RUB",
      "sales": "0"
    },
    {
      "id": "3949758",
      "name": "Firegirl",
      "full_name": "РюЁFiregirl: Hack 'n Splash Rescue DXРџАSteam\\лалц+люлИЛђ\\Key",
      "price": "43",
      "img": "https://graph.digiseller.ru/img.ashx?id_d=3949758&maxlength=400",
      "buy_url": "https://www.digiseller.market/asp2/pay_wm.asp?id_d=3949758&aff_id=1150998",
      "product_url": "https://www.digiseller.market/product/3949758",
      "currency": "RUB",
      "sales": "0"
    },
    {
      "id": "3963725",
      "name": "Fishermurs",
      "full_name": "РюЁFishermursРџАSteam\\лалц+лњлхЛЂЛї люлИЛђ\\KeyРГљ+ лџл░ЛђЛѓлЙЛЄл║лИ­ЪѓА",
      "price": "10",
      "img": "https://graph.digiseller.ru/img.ashx?id_d=3963725&maxlength=400",
      "buy_url": "https://www.digiseller.market/asp2/pay_wm.asp?id_d=3963725&aff_id=1150998",
      "product_url": "https://www.digiseller.market/product/3963725",
      "currency": "RUB",
      "sales": "0"
    },
    {
      "id": "3956562",
      "name": "Flow",
      "full_name": "РюЁFlow:The SlidingРџАSteam\\лалц+лњлхЛЂЛї люлИЛђ\\KeyРГљ",
      "price": "13",
      "img": "https://graph.digiseller.ru/img.ashx?id_d=3956562&maxlength=400",
      "buy_url": "https://www.digiseller.market/asp2/pay_wm.asp?id_d=3956562&aff_id=1150998",
      "product_url": "https://www.digiseller.market/product/3956562",
      "currency": "RUB",
      "sales": "0"
    },
    {
      "id": "3795749",
      "name": "For The King",
      "full_name": "РюЁFor The King РџА Steam лалц+лАлЮлЊ KeyРГљ + ­ЪјЂ лЪлЙл┤л░ЛђлЙл║",
      "price": "70",
      "img": "https://graph.digiseller.ru/img.ashx?id_d=3795749&maxlength=400",
      "buy_url": "https://www.digiseller.market/asp2/pay_wm.asp?id_d=3795749&aff_id=1150998",
      "product_url": "https://www.digiseller.market/product/3795749",
      "currency": "RUB",
      "sales": "0"
    },
    {
      "id": "4340625",
      "name": "Forced Showdown",
      "full_name": "РюЁForced Showdown РџА Steam\\лалц+лњлхЛЂЛїлюлИЛђ\\KeyРГљ + ­ЪјЂлЉлЙлйЛЃЛЂ",
      "price": "49",
      "img": "https://graph.digiseller.ru/img.ashx?id_d=4340625&maxlength=400",
      "buy_url": "https://www.digiseller.market/asp2/pay_wm.asp?id_d=4340625&aff_id=1150998",
      "product_url": "https://www.digiseller.market/product/4340625",
      "currency": "RUB",
      "sales": "0"
    },
    {
      "id": "4798680",
      "name": "Garden Life",
      "full_name": "РюЁGarden Life: A Cozy Simulator РџАSteam\\лалц+люлИЛђ\\KeyРГљ  + ­ЪјЂ",
      "price": "53",
      "img": "https://graph.digiseller.ru/img.ashx?id_d=4798680&maxlength=400",
      "buy_url": "https://www.digiseller.market/asp2/pay_wm.asp?id_d=4798680&aff_id=1150998",
      "product_url": "https://www.digiseller.market/product/4798680",
      "currency": "RUB",
      "sales": "0"
    },
    {
      "id": "3792237",
      "name": "Ghost Trick",
      "full_name": "Ghost Trick: Phantom Detective РџА Steam лалц+лАлЮлЊ лџлЏл«лДРГљ + ­ЪјЂ лЪлЙл┤л░ЛђлЙл║",
      "price": "599",
      "img": "https://graph.digiseller.ru/img.ashx?id_d=3792237&maxlength=400",
      "buy_url": "https://www.digiseller.market/asp2/pay_wm.asp?id_d=3792237&aff_id=1150998",
      "product_url": "https://www.digiseller.market/product/3792237",
      "currency": "RUB",
      "sales": "0"
    },
    {
      "id": "3890909",
      "name": "Girls Divers",
      "full_name": "РюЁGirls DiversРџАSteam\\лалц+лњлхЛЂЛїлюлИЛђ\\KeyРГљ",
      "price": "15",
      "img": "https://graph.digiseller.ru/img.ashx?id_d=3890909&maxlength=400",
      "buy_url": "https://www.digiseller.market/asp2/pay_wm.asp?id_d=3890909&aff_id=1150998",
      "product_url": "https://www.digiseller.market/product/3890909",
      "currency": "RUB",
      "sales": "0"
    },
    {
      "id": "3977908",
      "name": "Gloomhaven",
      "full_name": "Gloomhaven РџА Steam лалц+лАлЮлЊ лџлЏл«лДРГљ + ­ЪјЂ лЪлЙл┤л░ЛђлЙл║",
      "price": "499",
      "img": "https://graph.digiseller.ru/img.ashx?id_d=3977908&maxlength=400",
      "buy_url": "https://www.digiseller.market/asp2/pay_wm.asp?id_d=3977908&aff_id=1150998",
      "product_url": "https://www.digiseller.market/product/3977908",
      "currency": "RUB",
      "sales": "0"
    },
    {
      "id": "3778302",
      "name": "Golden Light",
      "full_name": "РюЁGolden Light РџАSteam лалц+люлИЛђ KeyРГљ + ­ЪјЂ лЉлЙлйЛЃЛЂ",
      "price": "60",
      "img": "https://graph.digiseller.ru/img.ashx?id_d=3778302&maxlength=400",
      "buy_url": "https://www.digiseller.market/asp2/pay_wm.asp?id_d=3778302&aff_id=1150998",
      "product_url": "https://www.digiseller.market/product/3778302",
      "currency": "RUB",
      "sales": "0"
    },
    {
      "id": "3895225",
      "name": "Golf Gang",
      "full_name": "Golf Gang РџАSteam лалц+люлИЛђ Key РГљ + ­ЪјЂ лЉлЙлйЛЃЛЂ",
      "price": "45",
      "img": "https://graph.digiseller.ru/img.ashx?id_d=3895225&maxlength=400",
      "buy_url": "https://www.digiseller.market/asp2/pay_wm.asp?id_d=3895225&aff_id=1150998",
      "product_url": "https://www.digiseller.market/product/3895225",
      "currency": "RUB",
      "sales": "0"
    },
    {
      "id": "3967405",
      "name": "Grave Prosperity",
      "full_name": "РюЁGrave Prosperity: Redux- part 1РџАSteam\\лалц+лњлхЛЂЛїлюлИЛђ\\KeyРГљ",
      "price": "79",
      "img": "https://graph.digiseller.ru/img.ashx?id_d=3967405&maxlength=400",
      "buy_url": "https://www.digiseller.market/asp2/pay_wm.asp?id_d=3967405&aff_id=1150998",
      "product_url": "https://www.digiseller.market/product/3967405",
      "currency": "RUB",
      "sales": "0"
    },
    {
      "id": "3962548",
      "name": "Greed and Grind",
      "full_name": "РюЁGreed and GrindРџАSteam\\лалц+лњлхЛЂЛїлюлИЛђ\\KeyРГљ",
      "price": "30",
      "img": "https://graph.digiseller.ru/img.ashx?id_d=3962548&maxlength=400",
      "buy_url": "https://www.digiseller.market/asp2/pay_wm.asp?id_d=3962548&aff_id=1150998",
      "product_url": "https://www.digiseller.market/product/3962548",
      "currency": "RUB",
      "sales": "0"
    },
    {
      "id": "3788710",
      "name": "GRIME",
      "full_name": "РюЁGRIME РџА Steam лалц+лАлЮлЊ лџлЏл«лДРГљ + ­ЪјЂ лЪлЙл┤л░ЛђлЙл║",
      "price": "209",
      "img": "https://graph.digiseller.ru/img.ashx?id_d=3788710&maxlength=400",
      "buy_url": "https://www.digiseller.market/asp2/pay_wm.asp?id_d=3788710&aff_id=1150998",
      "product_url": "https://www.digiseller.market/product/3788710",
      "currency": "RUB",
      "sales": "0"
    },
    {
      "id": "3791767",
      "name": "Hands of Necromancy",
      "full_name": "РюЁHands of NecromancyРџАSteam\\лалц+лњлхЛЂЛїлюлИЛђ\\KeyРГљ + ­ЪјЂлЉлЙлйЛЃЛЂ",
      "price": "43",
      "img": "https://graph.digiseller.ru/img.ashx?id_d=3791767&maxlength=400",
      "buy_url": "https://www.digiseller.market/asp2/pay_wm.asp?id_d=3791767&aff_id=1150998",
      "product_url": "https://www.digiseller.market/product/3791767",
      "currency": "RUB",
      "sales": "0"
    },
    {
      "id": "4019362",
      "name": "Happy",
      "full_name": "РюЁHappyРџАSteam\\лалц + лњлхЛЂЛї люлИЛђ\\KeyРГљ",
      "price": "250",
      "img": "https://graph.digiseller.ru/img.ashx?id_d=4019362&maxlength=400",
      "buy_url": "https://www.digiseller.market/asp2/pay_wm.asp?id_d=4019362&aff_id=1150998",
      "product_url": "https://www.digiseller.market/product/4019362",
      "currency": "RUB",
      "sales": "0"
    },
    {
      "id": "3777477",
      "name": "Havendock",
      "full_name": "РюЁHavendock РџА Steam лалЙЛЂЛЂлИЛЈ + люлИЛђ лџл╗ЛјЛЄ",
      "price": "20",
      "img": "https://graph.digiseller.ru/img.ashx?id_d=3777477&maxlength=400",
      "buy_url": "https://www.digiseller.market/asp2/pay_wm.asp?id_d=3777477&aff_id=1150998",
      "product_url": "https://www.digiseller.market/product/3777477",
      "currency": "RUB",
      "sales": "0"
    },
    {
      "id": "3939558",
      "name": "Heavy Metal Machines",
      "full_name": "РюЁHeavy Metal MachinesРџАSteam\\лалц+лњлхЛЂЛїлюлИЛђ\\KeyРГљ",
      "price": "2499",
      "img": "https://graph.digiseller.ru/img.ashx?id_d=3939558&maxlength=400",
      "buy_url": "https://www.digiseller.market/asp2/pay_wm.asp?id_d=3939558&aff_id=1150998",
      "product_url": "https://www.digiseller.market/product/3939558",
      "currency": "RUB",
      "sales": "0"
    },
    {
      "id": "3795120",
      "name": "Hike Valley",
      "full_name": "РюЁHike ValleyРџАSteam\\лалц+лњлхЛЂЛїлюлИЛђ\\KeyРГљ",
      "price": "90",
      "img": "https://graph.digiseller.ru/img.ashx?id_d=3795120&maxlength=400",
      "buy_url": "https://www.digiseller.market/asp2/pay_wm.asp?id_d=3795120&aff_id=1150998",
      "product_url": "https://www.digiseller.market/product/3795120",
      "currency": "RUB",
      "sales": "0"
    },
    {
      "id": "3782781",
      "name": "Hold your houses",
      "full_name": "РюЁHold your housesРџАSteam\\лалц+лњлхЛЂЛї люлИЛђ\\KeyРГљ+ лџл░ЛђЛѓлЙЛЄл║лИ",
      "price": "13",
      "img": "https://graph.digiseller.ru/img.ashx?id_d=3782781&maxlength=400",
      "buy_url": "https://www.digiseller.market/asp2/pay_wm.asp?id_d=3782781&aff_id=1150998",
      "product_url": "https://www.digiseller.market/product/3782781",
      "currency": "RUB",
      "sales": "0"
    },
    {
      "id": "3935299",
      "name": "Hyper Gunsport",
      "full_name": "РюЁHyper GunsportРџАSteam\\лалц+лњлхЛЂЛїлюлИЛђ\\KeyРГљ",
      "price": "29",
      "img": "https://graph.digiseller.ru/img.ashx?id_d=3935299&maxlength=400",
      "buy_url": "https://www.digiseller.market/asp2/pay_wm.asp?id_d=3935299&aff_id=1150998",
      "product_url": "https://www.digiseller.market/product/3935299",
      "currency": "RUB",
      "sales": "0"
    },
    {
      "id": "3861496",
      "name": "Inside Soccer",
      "full_name": "РюЁInside SoccerРџАSteam\\лалц+лњлхЛЂЛїлюлИЛђ\\KeyРГљ",
      "price": "15",
      "img": "https://graph.digiseller.ru/img.ashx?id_d=3861496&maxlength=400",
      "buy_url": "https://www.digiseller.market/asp2/pay_wm.asp?id_d=3861496&aff_id=1150998",
      "product_url": "https://www.digiseller.market/product/3861496",
      "currency": "RUB",
      "sales": "0"
    },
    {
      "id": "3949762",
      "name": "Invincible Medusa",
      "full_name": "РюЁInvincible MedusaРџАSteam\\лалц+лњлхЛЂЛї люлИЛђ\\KeyРГљ",
      "price": "149",
      "img": "https://graph.digiseller.ru/img.ashx?id_d=3949762&maxlength=400",
      "buy_url": "https://www.digiseller.market/asp2/pay_wm.asp?id_d=3949762&aff_id=1150998",
      "product_url": "https://www.digiseller.market/product/3949762",
      "currency": "RUB",
      "sales": "0"
    },
    {
      "id": "3841799",
      "name": "Izmir",
      "full_name": "РюЁIzmir: An Independence SimulatorРџАSteam\\лалц+люлИЛђ\\KeyРГљ+ ­ЪјЂ",
      "price": "14",
      "img": "https://graph.digiseller.ru/img.ashx?id_d=3841799&maxlength=400",
      "buy_url": "https://www.digiseller.market/asp2/pay_wm.asp?id_d=3841799&aff_id=1150998",
      "product_url": "https://www.digiseller.market/product/3841799",
      "currency": "RUB",
      "sales": "0"
    },
    {
      "id": "3820825",
      "name": "Japanese goblins",
      "full_name": "РюЁJapanese goblinsРџАSteam\\лалц+лњлхЛЂЛїлюлИЛђ\\KeyРГљ",
      "price": "25",
      "img": "https://graph.digiseller.ru/img.ashx?id_d=3820825&maxlength=400",
      "buy_url": "https://www.digiseller.market/asp2/pay_wm.asp?id_d=3820825&aff_id=1150998",
      "product_url": "https://www.digiseller.market/product/3820825",
      "currency": "RUB",
      "sales": "0"
    },
    {
      "id": "3841797",
      "name": "Kalyzmyr",
      "full_name": "РюЁKalyzmyrРџАSteam\\лалц+лњлхЛЂЛїлюлИЛђ\\KeyРГљ + ­ЪјЂлЉлЙлйЛЃЛЂ",
      "price": "79",
      "img": "https://graph.digiseller.ru/img.ashx?id_d=3841797&maxlength=400",
      "buy_url": "https://www.digiseller.market/asp2/pay_wm.asp?id_d=3841797&aff_id=1150998",
      "product_url": "https://www.digiseller.market/product/3841797",
      "currency": "RUB",
      "sales": "0"
    },
    {
      "id": "3815939",
      "name": "Karma City Police",
      "full_name": "РюЁKarma City PoliceРџАSteam\\лалц+лњлхЛЂЛї люлИЛђ\\KeyРГљ + ­ЪјЂ лЉлЙлйЛЃЛЂ",
      "price": "40",
      "img": "https://graph.digiseller.ru/img.ashx?id_d=3815939&maxlength=400",
      "buy_url": "https://www.digiseller.market/asp2/pay_wm.asp?id_d=3815939&aff_id=1150998",
      "product_url": "https://www.digiseller.market/product/3815939",
      "currency": "RUB",
      "sales": "0"
    },
    {
      "id": "3939545",
      "name": "King Pig",
      "full_name": "РюЁKing PigРџАSteam\\лалц+лњлхЛЂЛїлюлИЛђ\\KeyРГљ",
      "price": "149",
      "img": "https://graph.digiseller.ru/img.ashx?id_d=3939545&maxlength=400",
      "buy_url": "https://www.digiseller.market/asp2/pay_wm.asp?id_d=3939545&aff_id=1150998",
      "product_url": "https://www.digiseller.market/product/3939545",
      "currency": "RUB",
      "sales": "0"
    },
    {
      "id": "3795123",
      "name": "Kitchen Simulator 2015",
      "full_name": "РюЁKitchen Simulator 2015РџАSteam\\лалц+люлИЛђ\\KeyРГљ + лџл░ЛђЛѓлЙЛЄл║лИ­ЪѓА",
      "price": "14",
      "img": "https://graph.digiseller.ru/img.ashx?id_d=3795123&maxlength=400",
      "buy_url": "https://www.digiseller.market/asp2/pay_wm.asp?id_d=3795123&aff_id=1150998",
      "product_url": "https://www.digiseller.market/product/3795123",
      "currency": "RUB",
      "sales": "0"
    },
    {
      "id": "4836694",
      "name": "Kona",
      "full_name": "РюЁKona РџАSteam\\лалц+лњлхЛЂЛї люлИЛђ\\KeyРГљ + ­ЪјЂ лЉлЙлйЛЃЛЂ",
      "price": "235",
      "img": "https://graph.digiseller.ru/img.ashx?id_d=4836694&maxlength=400",
      "buy_url": "https://www.digiseller.market/asp2/pay_wm.asp?id_d=4836694&aff_id=1150998",
      "product_url": "https://www.digiseller.market/product/4836694",
      "currency": "RUB",
      "sales": "0"
    },
    {
      "id": "3961660",
      "name": "Kuggs",
      "full_name": "РюЁKuggsРџАSteam\\лалц+лњлхЛЂЛї люлИЛђ\\KeyРГљ",
      "price": "15",
      "img": "https://graph.digiseller.ru/img.ashx?id_d=3961660&maxlength=400",
      "buy_url": "https://www.digiseller.market/asp2/pay_wm.asp?id_d=3961660&aff_id=1150998",
      "product_url": "https://www.digiseller.market/product/3961660",
      "currency": "RUB",
      "sales": "0"
    },
    {
      "id": "3974283",
      "name": "Labyronia Elements",
      "full_name": "РюЁLabyronia ElementsРџАSteam\\лалц+лњлхЛЂЛї люлИЛђ\\KeyРГљ",
      "price": "15",
      "img": "https://graph.digiseller.ru/img.ashx?id_d=3974283&maxlength=400",
      "buy_url": "https://www.digiseller.market/asp2/pay_wm.asp?id_d=3974283&aff_id=1150998",
      "product_url": "https://www.digiseller.market/product/3974283",
      "currency": "RUB",
      "sales": "0"
    },
    {
      "id": "3858021",
      "name": "Lair of the Clockwork God",
      "full_name": "РюЁLair of the Clockwork GodРџАSteam\\лалц+лњлхЛЂЛї люлИЛђ\\KeyРГљ + ­ЪјЂ",
      "price": "64",
      "img": "https://graph.digiseller.ru/img.ashx?id_d=3858021&maxlength=400",
      "buy_url": "https://www.digiseller.market/asp2/pay_wm.asp?id_d=3858021&aff_id=1150998",
      "product_url": "https://www.digiseller.market/product/3858021",
      "currency": "RUB",
      "sales": "0"
    },
    {
      "id": "3946089",
      "name": "Lattice Dancer",
      "full_name": "РюЁLattice DancerРџАSteam\\лалц+лњлхЛЂЛїлюлИЛђ\\KeyРГљ",
      "price": "30",
      "img": "https://graph.digiseller.ru/img.ashx?id_d=3946089&maxlength=400",
      "buy_url": "https://www.digiseller.market/asp2/pay_wm.asp?id_d=3946089&aff_id=1150998",
      "product_url": "https://www.digiseller.market/product/3946089",
      "currency": "RUB",
      "sales": "0"
    },
    {
      "id": "3963716",
      "name": "Life is Feudal",
      "full_name": "Life is Feudal: Your Own РџА Steam лалълАлАлўл»+люлўла лџлЏл«лДРГљ + ­ЪјЂ лЪлЙл┤л░ЛђлЙл║",
      "price": "189",
      "img": "https://graph.digiseller.ru/img.ashx?id_d=3963716&maxlength=400",
      "buy_url": "https://www.digiseller.market/asp2/pay_wm.asp?id_d=3963716&aff_id=1150998",
      "product_url": "https://www.digiseller.market/product/3963716",
      "currency": "RUB",
      "sales": "0"
    },
    {
      "id": "3828542",
      "name": "Life is Strange",
      "full_name": "РюЁLife is Strange: Before the StormРџАSteam\\лалц+люлИЛђ\\Key +­ЪјЂ",
      "price": "669",
      "img": "https://graph.digiseller.ru/img.ashx?id_d=3828542&maxlength=400",
      "buy_url": "https://www.digiseller.market/asp2/pay_wm.asp?id_d=3828542&aff_id=1150998",
      "product_url": "https://www.digiseller.market/product/3828542",
      "currency": "RUB",
      "sales": "0"
    },
    {
      "id": "3939393",
      "name": "Lilly's Flower Shop",
      "full_name": "РюЁLilly's Flower ShopРџАSteam\\лалц+лњлхЛЂЛїлюлИЛђ\\KeyРГљ",
      "price": "30",
      "img": "https://graph.digiseller.ru/img.ashx?id_d=3939393&maxlength=400",
      "buy_url": "https://www.digiseller.market/asp2/pay_wm.asp?id_d=3939393&aff_id=1150998",
      "product_url": "https://www.digiseller.market/product/3939393",
      "currency": "RUB",
      "sales": "0"
    },
    {
      "id": "3820835",
      "name": "Loop Kingdom",
      "full_name": "РюЁLoop KingdomРџАSteam\\лалц+лњлхЛЂЛїлюлИЛђ\\KeyРГљ",
      "price": "49",
      "img": "https://graph.digiseller.ru/img.ashx?id_d=3820835&maxlength=400",
      "buy_url": "https://www.digiseller.market/asp2/pay_wm.asp?id_d=3820835&aff_id=1150998",
      "product_url": "https://www.digiseller.market/product/3820835",
      "currency": "RUB",
      "sales": "0"
    },
    {
      "id": "3916402",
      "name": "Lord of the Dark Castle",
      "full_name": "РюЁLord of the Dark CastleРџАSteam\\Global\\KeyРГљ+ лџл░ЛђЛѓлЙЛЄл║лИ­ЪѓА",
      "price": "14",
      "img": "https://graph.digiseller.ru/img.ashx?id_d=3916402&maxlength=400",
      "buy_url": "https://www.digiseller.market/asp2/pay_wm.asp?id_d=3916402&aff_id=1150998",
      "product_url": "https://www.digiseller.market/product/3916402",
      "currency": "RUB",
      "sales": "0"
    },
    {
      "id": "3935304",
      "name": "Lucifer Within Us",
      "full_name": "РюЁLucifer Within UsРџАSteam\\лалц+лњлхЛЂЛї люлИЛђ\\KeyРГљ + ­ЪјЂлЉлЙлйЛЃЛЂ",
      "price": "349",
      "img": "https://graph.digiseller.ru/img.ashx?id_d=3935304&maxlength=400",
      "buy_url": "https://www.digiseller.market/asp2/pay_wm.asp?id_d=3935304&aff_id=1150998",
      "product_url": "https://www.digiseller.market/product/3935304",
      "currency": "RUB",
      "sales": "0"
    },
    {
      "id": "3858003",
      "name": "Ludus",
      "full_name": "РюЁLudusРџАSteam\\лалц+лњлхЛЂЛї люлИЛђ\\KeyРГљ + ­ЪјЂлЉлЙлйЛЃЛЂ",
      "price": "170",
      "img": "https://graph.digiseller.ru/img.ashx?id_d=3858003&maxlength=400",
      "buy_url": "https://www.digiseller.market/asp2/pay_wm.asp?id_d=3858003&aff_id=1150998",
      "product_url": "https://www.digiseller.market/product/3858003",
      "currency": "RUB",
      "sales": "0"
    },
    {
      "id": "3782795",
      "name": "Madness Chambers",
      "full_name": "РюЁMadness ChambersРџАSteam\\лалц+лњлхЛЂЛї люлИЛђ\\KeyРГљ",
      "price": "50",
      "img": "https://graph.digiseller.ru/img.ashx?id_d=3782795&maxlength=400",
      "buy_url": "https://www.digiseller.market/asp2/pay_wm.asp?id_d=3782795&aff_id=1150998",
      "product_url": "https://www.digiseller.market/product/3782795",
      "currency": "RUB",
      "sales": "0"
    },
    {
      "id": "3975310",
      "name": "Math Ball",
      "full_name": "РюЁMath BallРџАSteam\\лалц+лњлхЛЂЛї люлИЛђ\\KeyРГљ",
      "price": "149",
      "img": "https://graph.digiseller.ru/img.ashx?id_d=3975310&maxlength=400",
      "buy_url": "https://www.digiseller.market/asp2/pay_wm.asp?id_d=3975310&aff_id=1150998",
      "product_url": "https://www.digiseller.market/product/3975310",
      "currency": "RUB",
      "sales": "0"
    },
    {
      "id": "3993254",
      "name": "Maverta Island",
      "full_name": "РюЁMaverta IslandРџАSteam\\лалц+лњлхЛЂЛї люлИЛђ\\KeyРГљ",
      "price": "15",
      "img": "https://graph.digiseller.ru/img.ashx?id_d=3993254&maxlength=400",
      "buy_url": "https://www.digiseller.market/asp2/pay_wm.asp?id_d=3993254&aff_id=1150998",
      "product_url": "https://www.digiseller.market/product/3993254",
      "currency": "RUB",
      "sales": "0"
    },
    {
      "id": "3956553",
      "name": "Maze Art",
      "full_name": "РюЁMaze Art: BlueРџАSteam\\лалц+лњлхЛЂЛї люлИЛђ\\KeyРГљ",
      "price": "10",
      "img": "https://graph.digiseller.ru/img.ashx?id_d=3956553&maxlength=400",
      "buy_url": "https://www.digiseller.market/asp2/pay_wm.asp?id_d=3956553&aff_id=1150998",
      "product_url": "https://www.digiseller.market/product/3956553",
      "currency": "RUB",
      "sales": "0"
    },
    {
      "id": "3975311",
      "name": "Maze Art",
      "full_name": "РюЁMaze Art: RainbowРџАSteam\\лалц+лњлхЛЂЛї люлИЛђ\\KeyРГљ",
      "price": "10",
      "img": "https://graph.digiseller.ru/img.ashx?id_d=3975311&maxlength=400",
      "buy_url": "https://www.digiseller.market/asp2/pay_wm.asp?id_d=3975311&aff_id=1150998",
      "product_url": "https://www.digiseller.market/product/3975311",
      "currency": "RUB",
      "sales": "0"
    },
    {
      "id": "3838236",
      "name": "Meadow",
      "full_name": "РюЁMeadow - A Shelter GameРџАSteam\\лалц+люлИЛђ\\KeyРГљ + ­ЪјЂлЉлЙлйЛЃЛЂ",
      "price": "75",
      "img": "https://graph.digiseller.ru/img.ashx?id_d=3838236&maxlength=400",
      "buy_url": "https://www.digiseller.market/asp2/pay_wm.asp?id_d=3838236&aff_id=1150998",
      "product_url": "https://www.digiseller.market/product/3838236",
      "currency": "RUB",
      "sales": "0"
    },
    {
      "id": "3820824",
      "name": "MechDefender",
      "full_name": "РюЁMechDefender - Tower Defense РџА Steam\\люлИЛђРГљ+ лџл░ЛђЛѓлЙЛЄл║лИ­ЪѓА",
      "price": "13",
      "img": "https://graph.digiseller.ru/img.ashx?id_d=3820824&maxlength=400",
      "buy_url": "https://www.digiseller.market/asp2/pay_wm.asp?id_d=3820824&aff_id=1150998",
      "product_url": "https://www.digiseller.market/product/3820824",
      "currency": "RUB",
      "sales": "0"
    },
    {
      "id": "3966726",
      "name": "Meekanoid",
      "full_name": "РюЁMeekanoidРџАSteam\\лалц+лњлхЛЂЛї люлИЛђ\\KeyРГљ",
      "price": "7",
      "img": "https://graph.digiseller.ru/img.ashx?id_d=3966726&maxlength=400",
      "buy_url": "https://www.digiseller.market/asp2/pay_wm.asp?id_d=3966726&aff_id=1150998",
      "product_url": "https://www.digiseller.market/product/3966726",
      "currency": "RUB",
      "sales": "0"
    },
    {
      "id": "3853367",
      "name": "Metro 2033 Redux",
      "full_name": "РюЁMetro 2033 ReduxРџА Steam\\лалц+лАлЮлЊ\\KeyРГљ + ­ЪјЂ лЉлЙлйЛЃЛЂ",
      "price": "98",
      "img": "https://graph.digiseller.ru/img.ashx?id_d=3853367&maxlength=400",
      "buy_url": "https://www.digiseller.market/asp2/pay_wm.asp?id_d=3853367&aff_id=1150998",
      "product_url": "https://www.digiseller.market/product/3853367",
      "currency": "RUB",
      "sales": "0"
    },
    {
      "id": "3853359",
      "name": "Metro",
      "full_name": "РюЁMetro: Last Light Redux  Steam лалц+лАлЮлЊ лџлЏл«лДРГљ + ­ЪјЂ лЉлЙлйЛЃЛЂ",
      "price": "119",
      "img": "https://graph.digiseller.ru/img.ashx?id_d=3853359&maxlength=400",
      "buy_url": "https://www.digiseller.market/asp2/pay_wm.asp?id_d=3853359&aff_id=1150998",
      "product_url": "https://www.digiseller.market/product/3853359",
      "currency": "RUB",
      "sales": "0"
    },
    {
      "id": "3890895",
      "name": "Midnight Ohota",
      "full_name": "РюЁMidnight OhotaРџАSteam\\лалц+лњлхЛЂЛїлюлИЛђ\\KeyРГљ",
      "price": "40",
      "img": "https://graph.digiseller.ru/img.ashx?id_d=3890895&maxlength=400",
      "buy_url": "https://www.digiseller.market/asp2/pay_wm.asp?id_d=3890895&aff_id=1150998",
      "product_url": "https://www.digiseller.market/product/3890895",
      "currency": "RUB",
      "sales": "0"
    },
    {
      "id": "3838234",
      "name": "Molecular Warfare",
      "full_name": "РюЁMolecular WarfareРџАSteam\\лалц+лњлхЛЂЛїлюлИЛђ\\KeyРГљ",
      "price": "30",
      "img": "https://graph.digiseller.ru/img.ashx?id_d=3838234&maxlength=400",
      "buy_url": "https://www.digiseller.market/asp2/pay_wm.asp?id_d=3838234&aff_id=1150998",
      "product_url": "https://www.digiseller.market/product/3838234",
      "currency": "RUB",
      "sales": "0"
    },
    {
      "id": "3946143",
      "name": "Moleshine Cooking Simulator",
      "full_name": "РюЁMoleshine Cooking SimulatorРџАSteam\\лалц+лњлхЛЂЛїлюлИЛђ\\KeyРГљ",
      "price": "30",
      "img": "https://graph.digiseller.ru/img.ashx?id_d=3946143&maxlength=400",
      "buy_url": "https://www.digiseller.market/asp2/pay_wm.asp?id_d=3946143&aff_id=1150998",
      "product_url": "https://www.digiseller.market/product/3946143",
      "currency": "RUB",
      "sales": "0"
    },
    {
      "id": "3782800",
      "name": "Monster Phenomenon",
      "full_name": "РюЁMonster PhenomenonРџАSteam\\лалц+лњлхЛЂЛї люлИЛђ\\KeyРГљ",
      "price": "149",
      "img": "https://graph.digiseller.ru/img.ashx?id_d=3782800&maxlength=400",
      "buy_url": "https://www.digiseller.market/asp2/pay_wm.asp?id_d=3782800&aff_id=1150998",
      "product_url": "https://www.digiseller.market/product/3782800",
      "currency": "RUB",
      "sales": "0"
    },
    {
      "id": "3963756",
      "name": "mrFOX",
      "full_name": "РюЁmrFOXРџАSteam\\лалц+лњлхЛЂЛї люлИЛђ\\KeyРГљ",
      "price": "199",
      "img": "https://graph.digiseller.ru/img.ashx?id_d=3963756&maxlength=400",
      "buy_url": "https://www.digiseller.market/asp2/pay_wm.asp?id_d=3963756&aff_id=1150998",
      "product_url": "https://www.digiseller.market/product/3963756",
      "currency": "RUB",
      "sales": "0"
    },
    {
      "id": "3975307",
      "name": "Nash Racing",
      "full_name": "РюЁNash Racing: 70 secondsРџАSteam\\лалц+лњлхЛЂЛї люлИЛђ\\KeyРГљ",
      "price": "19",
      "img": "https://graph.digiseller.ru/img.ashx?id_d=3975307&maxlength=400",
      "buy_url": "https://www.digiseller.market/asp2/pay_wm.asp?id_d=3975307&aff_id=1150998",
      "product_url": "https://www.digiseller.market/product/3975307",
      "currency": "RUB",
      "sales": "0"
    },
    {
      "id": "3949765",
      "name": "Native Problems",
      "full_name": "РюЁNative ProblemsРџАSteam\\лалц+лњлхЛЂЛї люлИЛђ\\KeyРГљ",
      "price": "149",
      "img": "https://graph.digiseller.ru/img.ashx?id_d=3949765&maxlength=400",
      "buy_url": "https://www.digiseller.market/asp2/pay_wm.asp?id_d=3949765&aff_id=1150998",
      "product_url": "https://www.digiseller.market/product/3949765",
      "currency": "RUB",
      "sales": "0"
    },
    {
      "id": "3783211",
      "name": "Nearly Dead Live and Let Die",
      "full_name": "РюЁNearly Dead Live and Let DieРџАSteam\\лњлхЛЂЛї люлИЛђ\\KeyРГљ+­ЪјЂ",
      "price": "160",
      "img": "https://graph.digiseller.ru/img.ashx?id_d=3783211&maxlength=400",
      "buy_url": "https://www.digiseller.market/asp2/pay_wm.asp?id_d=3783211&aff_id=1150998",
      "product_url": "https://www.digiseller.market/product/3783211",
      "currency": "RUB",
      "sales": "0"
    },
    {
      "id": "3780685",
      "name": "NecroBouncer",
      "full_name": "РюЁNecroBouncer РџА Steam\\лалц+лњлхЛЂЛїлюлИЛђ\\KeyРГљ + ­ЪјЂлЉлЙлйЛЃЛЂ",
      "price": "110",
      "img": "https://graph.digiseller.ru/img.ashx?id_d=3780685&maxlength=400",
      "buy_url": "https://www.digiseller.market/asp2/pay_wm.asp?id_d=3780685&aff_id=1150998",
      "product_url": "https://www.digiseller.market/product/3780685",
      "currency": "RUB",
      "sales": "0"
    },
    {
      "id": "3939387",
      "name": "Neon Fantasy",
      "full_name": "РюЁNeon Fantasy: FurriesРџАSteam\\лалц+лњлхЛЂЛїлюлИЛђ\\KeyРГљ",
      "price": "15",
      "img": "https://graph.digiseller.ru/img.ashx?id_d=3939387&maxlength=400",
      "buy_url": "https://www.digiseller.market/asp2/pay_wm.asp?id_d=3939387&aff_id=1150998",
      "product_url": "https://www.digiseller.market/product/3939387",
      "currency": "RUB",
      "sales": "0"
    },
    {
      "id": "3820831",
      "name": "Neon Fantasy",
      "full_name": "РюЁNeon Fantasy: GirlsРџАSteam\\лалц+лњлхЛЂЛїлюлИЛђ\\KeyРГљ",
      "price": "15",
      "img": "https://graph.digiseller.ru/img.ashx?id_d=3820831&maxlength=400",
      "buy_url": "https://www.digiseller.market/asp2/pay_wm.asp?id_d=3820831&aff_id=1150998",
      "product_url": "https://www.digiseller.market/product/3820831",
      "currency": "RUB",
      "sales": "0"
    },
    {
      "id": "3803790",
      "name": "Nickelodeon Kart Racers",
      "full_name": "РюЁNickelodeon Kart Racers 2: Grand Prix Steam лалц+люлИЛђ лџл╗ЛјЛЄРГљ + лЪлЙл┤л░ЛђлЙл║",
      "price": "85",
      "img": "https://graph.digiseller.ru/img.ashx?id_d=3803790&maxlength=400",
      "buy_url": "https://www.digiseller.market/asp2/pay_wm.asp?id_d=3803790&aff_id=1150998",
      "product_url": "https://www.digiseller.market/product/3803790",
      "currency": "RUB",
      "sales": "0"
    },
    {
      "id": "3783217",
      "name": "Nightmare Slash",
      "full_name": "РюЁNightmare SlashРџАSteam\\лалц+лњлхЛЂЛї люлИЛђ\\KeyРГљ",
      "price": "149",
      "img": "https://graph.digiseller.ru/img.ashx?id_d=3783217&maxlength=400",
      "buy_url": "https://www.digiseller.market/asp2/pay_wm.asp?id_d=3783217&aff_id=1150998",
      "product_url": "https://www.digiseller.market/product/3783217",
      "currency": "RUB",
      "sales": "0"
    },
    {
      "id": "4285402",
      "name": "Nobody Wants to Die",
      "full_name": "РюЁNobody Wants to DieРџА Steam\\ лЋл▓ЛђлЙл┐л░+лљл╝лхЛђлИл║л░ + л┤ЛђЛЃл│лИлх + ­ЪјЂ Bonus",
      "price": "99",
      "img": "https://graph.digiseller.ru/img.ashx?id_d=4285402&maxlength=400",
      "buy_url": "https://www.digiseller.market/asp2/pay_wm.asp?id_d=4285402&aff_id=1150998",
      "product_url": "https://www.digiseller.market/product/4285402",
      "currency": "RUB",
      "sales": "0"
    },
    {
      "id": "3782801",
      "name": "NOT the Hero",
      "full_name": "РюЁNOT the HeroРџАSteam\\лалц+лњлхЛЂЛї люлИЛђ\\KeyРГљ",
      "price": "15",
      "img": "https://graph.digiseller.ru/img.ashx?id_d=3782801&maxlength=400",
      "buy_url": "https://www.digiseller.market/asp2/pay_wm.asp?id_d=3782801&aff_id=1150998",
      "product_url": "https://www.digiseller.market/product/3782801",
      "currency": "RUB",
      "sales": "0"
    },
    {
      "id": "3974281",
      "name": "Octopus Island",
      "full_name": "РюЁOctopus IslandРџАSteam\\лалц+лњлхЛЂЛї люлИЛђ\\KeyРГљ",
      "price": "250",
      "img": "https://graph.digiseller.ru/img.ashx?id_d=3974281&maxlength=400",
      "buy_url": "https://www.digiseller.market/asp2/pay_wm.asp?id_d=3974281&aff_id=1150998",
      "product_url": "https://www.digiseller.market/product/3974281",
      "currency": "RUB",
      "sales": "0"
    },
    {
      "id": "4908758",
      "name": "Only Up",
      "full_name": "РюЁOnly Up: BRAINROT TOGETHERРџАSteam\\лалц+лњлхЛЂЛї люлИЛђ\\KeyРГљ + ­ЪјЂ",
      "price": "20",
      "img": "https://graph.digiseller.ru/img.ashx?id_d=4908758&maxlength=400",
      "buy_url": "https://www.digiseller.market/asp2/pay_wm.asp?id_d=4908758&aff_id=1150998",
      "product_url": "https://www.digiseller.market/product/4908758",
      "currency": "RUB",
      "sales": "0"
    },
    {
      "id": "3966722",
      "name": "Operation swat",
      "full_name": "РюЁOperation swatРџАSteam\\лалц+лњлхЛЂЛї люлИЛђ\\KeyРГљ+ лџл░ЛђЛѓлЙЛЄл║лИ­ЪѓА",
      "price": "14",
      "img": "https://graph.digiseller.ru/img.ashx?id_d=3966722&maxlength=400",
      "buy_url": "https://www.digiseller.market/asp2/pay_wm.asp?id_d=3966722&aff_id=1150998",
      "product_url": "https://www.digiseller.market/product/3966722",
      "currency": "RUB",
      "sales": "0"
    },
    {
      "id": "3777878",
      "name": "PAYDAY",
      "full_name": "РюЁPAYDAY 2 РџАSteam\\лалц+лАлЮлЊ\\KeyРГљ + ­ЪјЂлЉлЙлйЛЃЛЂ",
      "price": "489",
      "img": "https://graph.digiseller.ru/img.ashx?id_d=3777878&maxlength=400",
      "buy_url": "https://www.digiseller.market/asp2/pay_wm.asp?id_d=3777878&aff_id=1150998",
      "product_url": "https://www.digiseller.market/product/3777878",
      "currency": "RUB",
      "sales": "0"
    },
    {
      "id": "3977905",
      "name": "Petty's Adventure",
      "full_name": "РюЁPetty's Adventure: VolcanoРџАSteam\\лалц+лњлхЛЂЛї люлИЛђ\\KeyРГљ",
      "price": "15",
      "img": "https://graph.digiseller.ru/img.ashx?id_d=3977905&maxlength=400",
      "buy_url": "https://www.digiseller.market/asp2/pay_wm.asp?id_d=3977905&aff_id=1150998",
      "product_url": "https://www.digiseller.market/product/3977905",
      "currency": "RUB",
      "sales": "0"
    },
    {
      "id": "3956862",
      "name": "Pew Pew Rocket!",
      "full_name": "РюЁPew Pew Rocket!РџАSteam\\лалц+лњлхЛЂЛї люлИЛђ\\KeyРГљ",
      "price": "15",
      "img": "https://graph.digiseller.ru/img.ashx?id_d=3956862&maxlength=400",
      "buy_url": "https://www.digiseller.market/asp2/pay_wm.asp?id_d=3956862&aff_id=1150998",
      "product_url": "https://www.digiseller.market/product/3956862",
      "currency": "RUB",
      "sales": "0"
    },
    {
      "id": "3946092",
      "name": "Pick Up The Waste",
      "full_name": "РюЁPick Up The WasteРџАSteam\\лалц+лњлхЛЂЛїлюлИЛђ\\KeyРГљ",
      "price": "15",
      "img": "https://graph.digiseller.ru/img.ashx?id_d=3946092&maxlength=400",
      "buy_url": "https://www.digiseller.market/asp2/pay_wm.asp?id_d=3946092&aff_id=1150998",
      "product_url": "https://www.digiseller.market/product/3946092",
      "currency": "RUB",
      "sales": "0"
    },
    {
      "id": "3841796",
      "name": "Planet TD",
      "full_name": "РюЁPlanet TDРџАSteam\\лалц+лњлхЛЂЛїлюлИЛђ\\KeyРГљ + ­ЪјЂлЉлЙлйЛЃЛЂ",
      "price": "15",
      "img": "https://graph.digiseller.ru/img.ashx?id_d=3841796&maxlength=400",
      "buy_url": "https://www.digiseller.market/asp2/pay_wm.asp?id_d=3841796&aff_id=1150998",
      "product_url": "https://www.digiseller.market/product/3841796",
      "currency": "RUB",
      "sales": "0"
    },
    {
      "id": "3975313",
      "name": "POG",
      "full_name": "РюЁPOG 7РџАSteam\\лалц+лњлхЛЂЛї люлИЛђ\\KeyРГљ",
      "price": "8",
      "img": "https://graph.digiseller.ru/img.ashx?id_d=3975313&maxlength=400",
      "buy_url": "https://www.digiseller.market/asp2/pay_wm.asp?id_d=3975313&aff_id=1150998",
      "product_url": "https://www.digiseller.market/product/3975313",
      "currency": "RUB",
      "sales": "0"
    },
    {
      "id": "3966724",
      "name": "Poly Jigsaw",
      "full_name": "РюЁPoly Jigsaw: FurriesРџАSteam\\лалц+лњлхЛЂЛї люлИЛђ\\KeyРГљ",
      "price": "15",
      "img": "https://graph.digiseller.ru/img.ashx?id_d=3966724&maxlength=400",
      "buy_url": "https://www.digiseller.market/asp2/pay_wm.asp?id_d=3966724&aff_id=1150998",
      "product_url": "https://www.digiseller.market/product/3966724",
      "currency": "RUB",
      "sales": "0"
    },
    {
      "id": "3861523",
      "name": "Poly Jigsaw",
      "full_name": "РюЁPoly Jigsaw: PredatorsРџАSteam\\лалц+лњлхЛЂЛїлюлИЛђ\\KeyРГљ",
      "price": "15",
      "img": "https://graph.digiseller.ru/img.ashx?id_d=3861523&maxlength=400",
      "buy_url": "https://www.digiseller.market/asp2/pay_wm.asp?id_d=3861523&aff_id=1150998",
      "product_url": "https://www.digiseller.market/product/3861523",
      "currency": "RUB",
      "sales": "0"
    },
    {
      "id": "3975309",
      "name": "Poly Puzzle",
      "full_name": "РюЁPoly Puzzle: DogsРџАSteam\\лалц+лњлхЛЂЛї люлИЛђ\\KeyРГљ",
      "price": "8",
      "img": "https://graph.digiseller.ru/img.ashx?id_d=3975309&maxlength=400",
      "buy_url": "https://www.digiseller.market/asp2/pay_wm.asp?id_d=3975309&aff_id=1150998",
      "product_url": "https://www.digiseller.market/product/3975309",
      "currency": "RUB",
      "sales": "0"
    },
    {
      "id": "3963745",
      "name": "Primal Age",
      "full_name": "РюЁPrimal AgeРџАSteam\\лалц+лњлхЛЂЛї люлИЛђ\\KeyРГљ",
      "price": "149",
      "img": "https://graph.digiseller.ru/img.ashx?id_d=3963745&maxlength=400",
      "buy_url": "https://www.digiseller.market/asp2/pay_wm.asp?id_d=3963745&aff_id=1150998",
      "product_url": "https://www.digiseller.market/product/3963745",
      "currency": "RUB",
      "sales": "0"
    },
    {
      "id": "4019341",
      "name": "Pug With Bomb",
      "full_name": "РюЁPug With BombРџАSteam\\лалц + лњлхЛЂЛї люлИЛђ\\KeyРГљ",
      "price": "149",
      "img": "https://graph.digiseller.ru/img.ashx?id_d=4019341&maxlength=400",
      "buy_url": "https://www.digiseller.market/asp2/pay_wm.asp?id_d=4019341&aff_id=1150998",
      "product_url": "https://www.digiseller.market/product/4019341",
      "currency": "RUB",
      "sales": "0"
    },
    {
      "id": "3939564",
      "name": "Puzzle Art",
      "full_name": "РюЁPuzzle Art: CatsРџАSteam\\лалц+лњлхЛЂЛїлюлИЛђ\\KeyРГљ",
      "price": "15",
      "img": "https://graph.digiseller.ru/img.ashx?id_d=3939564&maxlength=400",
      "buy_url": "https://www.digiseller.market/asp2/pay_wm.asp?id_d=3939564&aff_id=1150998",
      "product_url": "https://www.digiseller.market/product/3939564",
      "currency": "RUB",
      "sales": "0"
    },
    {
      "id": "3939395",
      "name": "Puzzle Art",
      "full_name": "РюЁPuzzle Art: ReptilesРџАSteam\\лалц+лњлхЛЂЛїлюлИЛђ\\KeyРГљ",
      "price": "15",
      "img": "https://graph.digiseller.ru/img.ashx?id_d=3939395&maxlength=400",
      "buy_url": "https://www.digiseller.market/asp2/pay_wm.asp?id_d=3939395&aff_id=1150998",
      "product_url": "https://www.digiseller.market/product/3939395",
      "currency": "RUB",
      "sales": "0"
    },
    {
      "id": "3956576",
      "name": "Radiant Cell",
      "full_name": "РюЁRadiant CellРџАSteam\\лалц+лњлхЛЂЛї люлИЛђ\\KeyРГљ",
      "price": "20",
      "img": "https://graph.digiseller.ru/img.ashx?id_d=3956576&maxlength=400",
      "buy_url": "https://www.digiseller.market/asp2/pay_wm.asp?id_d=3956576&aff_id=1150998",
      "product_url": "https://www.digiseller.market/product/3956576",
      "currency": "RUB",
      "sales": "0"
    },
    {
      "id": "3861537",
      "name": "Red Flower",
      "full_name": "РюЁRed FlowerРџАSteam\\лалц+лњлхЛЂЛїлюлИЛђ\\KeyРГљ",
      "price": "15",
      "img": "https://graph.digiseller.ru/img.ashx?id_d=3861537&maxlength=400",
      "buy_url": "https://www.digiseller.market/asp2/pay_wm.asp?id_d=3861537&aff_id=1150998",
      "product_url": "https://www.digiseller.market/product/3861537",
      "currency": "RUB",
      "sales": "0"
    },
    {
      "id": "3861479",
      "name": "Reddish",
      "full_name": "РюЁReddishРџАSteam\\лалц+лњлхЛЂЛї люлИЛђ\\KeyРГљ + ­ЪјЂлЉлЙлйЛЃЛЂ",
      "price": "99",
      "img": "https://graph.digiseller.ru/img.ashx?id_d=3861479&maxlength=400",
      "buy_url": "https://www.digiseller.market/asp2/pay_wm.asp?id_d=3861479&aff_id=1150998",
      "product_url": "https://www.digiseller.market/product/3861479",
      "currency": "RUB",
      "sales": "0"
    },
    {
      "id": "3977910",
      "name": "REFICUL 666",
      "full_name": "РюЁREFICUL 666РџАSteam\\лалц+лњлхЛЂЛї люлИЛђ\\KeyРГљ + ­ЪјЂлЉлЙлйЛЃЛЂ",
      "price": "399",
      "img": "https://graph.digiseller.ru/img.ashx?id_d=3977910&maxlength=400",
      "buy_url": "https://www.digiseller.market/asp2/pay_wm.asp?id_d=3977910&aff_id=1150998",
      "product_url": "https://www.digiseller.market/product/3977910",
      "currency": "RUB",
      "sales": "0"
    },
    {
      "id": "3882690",
      "name": "Rescue Elves",
      "full_name": "РюЁRescue ElvesРџАSteam\\лалц+лњлхЛЂЛїлюлИЛђ\\KeyРГљ",
      "price": "15",
      "img": "https://graph.digiseller.ru/img.ashx?id_d=3882690&maxlength=400",
      "buy_url": "https://www.digiseller.market/asp2/pay_wm.asp?id_d=3882690&aff_id=1150998",
      "product_url": "https://www.digiseller.market/product/3882690",
      "currency": "RUB",
      "sales": "0"
    },
    {
      "id": "3967407",
      "name": "Rescue Team",
      "full_name": "РюЁRescue Team 5РџАSteam\\лалц+лњлхЛЂЛїлюлИЛђ\\KeyРГљ",
      "price": "40",
      "img": "https://graph.digiseller.ru/img.ashx?id_d=3967407&maxlength=400",
      "buy_url": "https://www.digiseller.market/asp2/pay_wm.asp?id_d=3967407&aff_id=1150998",
      "product_url": "https://www.digiseller.market/product/3967407",
      "currency": "RUB",
      "sales": "0"
    },
    {
      "id": "3949761",
      "name": "Resident Evil",
      "full_name": "Resident Evil 4: Ultimate HD Edition РџА Steam лалц+лАлЮлЊ лџлЏл«лДРГљ + ­ЪјЂ лЪлЙл┤л░ЛђлЙл║",
      "price": "545",
      "img": "https://graph.digiseller.ru/img.ashx?id_d=3949761&maxlength=400",
      "buy_url": "https://www.digiseller.market/asp2/pay_wm.asp?id_d=3949761&aff_id=1150998",
      "product_url": "https://www.digiseller.market/product/3949761",
      "currency": "RUB",
      "sales": "0"
    },
    {
      "id": "3777712",
      "name": "Resident Evil Gold Edition",
      "full_name": "РюЁResident Evil 7 Gold Edition (лўл│Лђл░+4 DLC)РџА Steam лалц+лАлЮлЊ KeyРГљ",
      "price": "999",
      "img": "https://graph.digiseller.ru/img.ashx?id_d=3777712&maxlength=400",
      "buy_url": "https://www.digiseller.market/asp2/pay_wm.asp?id_d=3777712&aff_id=1150998",
      "product_url": "https://www.digiseller.market/product/3777712",
      "currency": "RUB",
      "sales": "0"
    },
    {
      "id": "3956570",
      "name": "Rhino's Rage",
      "full_name": "РюЁRhino's RageРџАSteam\\лалц+лњлхЛЂЛї люлИЛђ\\KeyРГљ+ лџл░ЛђЛѓлЙЛЄл║лИ­ЪѓА",
      "price": "18",
      "img": "https://graph.digiseller.ru/img.ashx?id_d=3956570&maxlength=400",
      "buy_url": "https://www.digiseller.market/asp2/pay_wm.asp?id_d=3956570&aff_id=1150998",
      "product_url": "https://www.digiseller.market/product/3956570",
      "currency": "RUB",
      "sales": "0"
    },
    {
      "id": "3971591",
      "name": "Rolling Toolman",
      "full_name": "РюЁRolling ToolmanРџАSteam\\лалц+лњлхЛЂЛїлюлИЛђ\\KeyРГљ",
      "price": "35",
      "img": "https://graph.digiseller.ru/img.ashx?id_d=3971591&maxlength=400",
      "buy_url": "https://www.digiseller.market/asp2/pay_wm.asp?id_d=3971591&aff_id=1150998",
      "product_url": "https://www.digiseller.market/product/3971591",
      "currency": "RUB",
      "sales": "0"
    },
    {
      "id": "3916395",
      "name": "RONIN",
      "full_name": "РюЁRONIN: Two Souls CHAPTER 1РџАSteam\\лалц+лњлхЛЂЛїлюлИЛђ\\KeyРГљ + ­ЪјЂ",
      "price": "45",
      "img": "https://graph.digiseller.ru/img.ashx?id_d=3916395&maxlength=400",
      "buy_url": "https://www.digiseller.market/asp2/pay_wm.asp?id_d=3916395&aff_id=1150998",
      "product_url": "https://www.digiseller.market/product/3916395",
      "currency": "RUB",
      "sales": "0"
    },
    {
      "id": "4019363",
      "name": "РюЁRUSSIAN FIGHT SIMULATORРџАSteam\\лалц + лњлхЛЂЛї люлИЛђ\\KeyРГљ",
      "full_name": "РюЁRUSSIAN FIGHT SIMULATORРџАSteam\\лалц + лњлхЛЂЛї люлИЛђ\\KeyРГљ",
      "price": "40",
      "img": "https://graph.digiseller.ru/img.ashx?id_d=4019363&maxlength=400",
      "buy_url": "https://www.digiseller.market/asp2/pay_wm.asp?id_d=4019363&aff_id=1150998",
      "product_url": "https://www.digiseller.market/product/4019363",
      "currency": "RUB",
      "sales": "0"
    },
    {
      "id": "3782790",
      "name": "Sacred Valley",
      "full_name": "РюЁSacred ValleyРџАSteam\\лалц+лњлхЛЂЛї люлИЛђ\\KeyРГљ",
      "price": "249",
      "img": "https://graph.digiseller.ru/img.ashx?id_d=3782790&maxlength=400",
      "buy_url": "https://www.digiseller.market/asp2/pay_wm.asp?id_d=3782790&aff_id=1150998",
      "product_url": "https://www.digiseller.market/product/3782790",
      "currency": "RUB",
      "sales": "0"
    },
    {
      "id": "3895200",
      "name": "SCARF",
      "full_name": "РюЁSCARFРџАSteam\\лалц+лњлхЛЂЛїлюлИЛђ\\KeyРГљ + ­ЪјЂлЉлЙлйЛЃЛЂ",
      "price": "280",
      "img": "https://graph.digiseller.ru/img.ashx?id_d=3895200&maxlength=400",
      "buy_url": "https://www.digiseller.market/asp2/pay_wm.asp?id_d=3895200&aff_id=1150998",
      "product_url": "https://www.digiseller.market/product/3895200",
      "currency": "RUB",
      "sales": "0"
    },
    {
      "id": "4087924",
      "name": "schoolbreak.io",
      "full_name": "РюЁschoolbreak.io РџАSteam\\лалц + лњлхЛЂЛї люлИЛђ\\KeyРГљ",
      "price": "199",
      "img": "https://graph.digiseller.ru/img.ashx?id_d=4087924&maxlength=400",
      "buy_url": "https://www.digiseller.market/asp2/pay_wm.asp?id_d=4087924&aff_id=1150998",
      "product_url": "https://www.digiseller.market/product/4087924",
      "currency": "RUB",
      "sales": "0"
    },
    {
      "id": "3882692",
      "name": "Self Shot",
      "full_name": "РюЁSelf ShotРџАSteam\\лалц+лњлхЛЂЛїлюлИЛђ\\KeyРГљ",
      "price": "20",
      "img": "https://graph.digiseller.ru/img.ashx?id_d=3882692&maxlength=400",
      "buy_url": "https://www.digiseller.market/asp2/pay_wm.asp?id_d=3882692&aff_id=1150998",
      "product_url": "https://www.digiseller.market/product/3882692",
      "currency": "RUB",
      "sales": "0"
    },
    {
      "id": "3861465",
      "name": "Sevyal",
      "full_name": "РюЁSevyalРџАSteam\\лалц+лњлхЛЂЛїлюлИЛђ\\KeyРГљ",
      "price": "99",
      "img": "https://graph.digiseller.ru/img.ashx?id_d=3861465&maxlength=400",
      "buy_url": "https://www.digiseller.market/asp2/pay_wm.asp?id_d=3861465&aff_id=1150998",
      "product_url": "https://www.digiseller.market/product/3861465",
      "currency": "RUB",
      "sales": "0"
    },
    {
      "id": "3946109",
      "name": "Shuttle World",
      "full_name": "РюЁShuttle World РџАSteam\\лалц+лњлхЛЂЛїлюлИЛђ\\KeyРГљ",
      "price": "45",
      "img": "https://graph.digiseller.ru/img.ashx?id_d=3946109&maxlength=400",
      "buy_url": "https://www.digiseller.market/asp2/pay_wm.asp?id_d=3946109&aff_id=1150998",
      "product_url": "https://www.digiseller.market/product/3946109",
      "currency": "RUB",
      "sales": "0"
    },
    {
      "id": "3992914",
      "name": "Siege Showdown",
      "full_name": "РюЁSiege ShowdownРџАSteam\\лалц+лњлхЛЂЛї люлИЛђ\\KeyРГљ",
      "price": "15",
      "img": "https://graph.digiseller.ru/img.ashx?id_d=3992914&maxlength=400",
      "buy_url": "https://www.digiseller.market/asp2/pay_wm.asp?id_d=3992914&aff_id=1150998",
      "product_url": "https://www.digiseller.market/product/3992914",
      "currency": "RUB",
      "sales": "0"
    },
    {
      "id": "3777825",
      "name": "Sker Ritual",
      "full_name": "РюЁSker Ritual РџА Steam лалЙЛЂЛЂлИЛЈ + люлИЛђ лџл╗ЛјЛЄ + лЉлЙлйЛЃc",
      "price": "135",
      "img": "https://graph.digiseller.ru/img.ashx?id_d=3777825&maxlength=400",
      "buy_url": "https://www.digiseller.market/asp2/pay_wm.asp?id_d=3777825&aff_id=1150998",
      "product_url": "https://www.digiseller.market/product/3777825",
      "currency": "RUB",
      "sales": "0"
    },
    {
      "id": "3838238",
      "name": "Skylar Plux",
      "full_name": "РюЁSkylar & Plux: Adventure On Clover IslandРџАSteam\\лалц+люлИЛђ",
      "price": "499",
      "img": "https://graph.digiseller.ru/img.ashx?id_d=3838238&maxlength=400",
      "buy_url": "https://www.digiseller.market/asp2/pay_wm.asp?id_d=3838238&aff_id=1150998",
      "product_url": "https://www.digiseller.market/product/3838238",
      "currency": "RUB",
      "sales": "0"
    },
    {
      "id": "3882682",
      "name": "Smiling Girls",
      "full_name": "РюЁSmiling GirlsРџАSteam\\лалц+лњлхЛЂЛїлюлИЛђ\\KeyРГљ",
      "price": "25",
      "img": "https://graph.digiseller.ru/img.ashx?id_d=3882682&maxlength=400",
      "buy_url": "https://www.digiseller.market/asp2/pay_wm.asp?id_d=3882682&aff_id=1150998",
      "product_url": "https://www.digiseller.market/product/3882682",
      "currency": "RUB",
      "sales": "0"
    },
    {
      "id": "5441191",
      "name": "Sniper Elite",
      "full_name": "Sniper Elite 5 Steam EUROPE+NA (лЉлхли лалц-лАлЮлЊ) лџл╗ЛјЛЄ",
      "price": "349",
      "img": "https://graph.digiseller.ru/img.ashx?id_d=5441191&maxlength=400",
      "buy_url": "https://www.digiseller.market/asp2/pay_wm.asp?id_d=5441191&aff_id=1150998",
      "product_url": "https://www.digiseller.market/product/5441191",
      "currency": "RUB",
      "sales": "0"
    },
    {
      "id": "3949754",
      "name": "Space Pilgrim Episode IV",
      "full_name": "РюЁSpace Pilgrim Episode IV: SolРџАSteam\\лалц+лњлхЛЂЛї люлИЛђ\\KeyРГљ",
      "price": "18",
      "img": "https://graph.digiseller.ru/img.ashx?id_d=3949754&maxlength=400",
      "buy_url": "https://www.digiseller.market/asp2/pay_wm.asp?id_d=3949754&aff_id=1150998",
      "product_url": "https://www.digiseller.market/product/3949754",
      "currency": "RUB",
      "sales": "0"
    },
    {
      "id": "3997026",
      "name": "SpaceDog",
      "full_name": "РюЁSpaceDogРџАSteam\\лалц + лњлхЛЂЛї люлИЛђ\\KeyРГљ",
      "price": "149",
      "img": "https://graph.digiseller.ru/img.ashx?id_d=3997026&maxlength=400",
      "buy_url": "https://www.digiseller.market/asp2/pay_wm.asp?id_d=3997026&aff_id=1150998",
      "product_url": "https://www.digiseller.market/product/3997026",
      "currency": "RUB",
      "sales": "0"
    },
    {
      "id": "3935302",
      "name": "Starpoint Gemini Warlords",
      "full_name": "РюЁStarpoint Gemini WarlordsРџАSteam\\лалц + люлИЛђ\\KeyРГљ + ­ЪјЂ",
      "price": "120",
      "img": "https://graph.digiseller.ru/img.ashx?id_d=3935302&maxlength=400",
      "buy_url": "https://www.digiseller.market/asp2/pay_wm.asp?id_d=3935302&aff_id=1150998",
      "product_url": "https://www.digiseller.market/product/3935302",
      "currency": "RUB",
      "sales": "0"
    },
    {
      "id": "3795121",
      "name": "StellarHub",
      "full_name": "РюЁStellarHubРџАSteam\\лалц+лњлхЛЂЛїлюлИЛђ\\KeyРГљ+ лџл░ЛђЛѓлЙЛЄл║лИ­ЪѓА",
      "price": "14",
      "img": "https://graph.digiseller.ru/img.ashx?id_d=3795121&maxlength=400",
      "buy_url": "https://www.digiseller.market/asp2/pay_wm.asp?id_d=3795121&aff_id=1150998",
      "product_url": "https://www.digiseller.market/product/3795121",
      "currency": "RUB",
      "sales": "0"
    },
    {
      "id": "3918619",
      "name": "Streamer Life Simulator",
      "full_name": "РюЁStreamer Life SimulatorРџАSteam\\лалц + люлИЛђ\\KeyРГљ + ­ЪјЂлЉлЙлйЛЃЛЂ",
      "price": "149",
      "img": "https://graph.digiseller.ru/img.ashx?id_d=3918619&maxlength=400",
      "buy_url": "https://www.digiseller.market/asp2/pay_wm.asp?id_d=3918619&aff_id=1150998",
      "product_url": "https://www.digiseller.market/product/3918619",
      "currency": "RUB",
      "sales": "0"
    },
    {
      "id": "3861413",
      "name": "StudyX",
      "full_name": "РюЁStudyX - Save Game Codes & Study Any SubjectРџАSteam\\люлИЛђ",
      "price": "100",
      "img": "https://graph.digiseller.ru/img.ashx?id_d=3861413&maxlength=400",
      "buy_url": "https://www.digiseller.market/asp2/pay_wm.asp?id_d=3861413&aff_id=1150998",
      "product_url": "https://www.digiseller.market/product/3861413",
      "currency": "RUB",
      "sales": "0"
    },
    {
      "id": "3882685",
      "name": "Subuccus",
      "full_name": "РюЁSubuccusРџАSteam\\лалц+лњлхЛЂЛїлюлИЛђ\\KeyРГљ",
      "price": "449",
      "img": "https://graph.digiseller.ru/img.ashx?id_d=3882685&maxlength=400",
      "buy_url": "https://www.digiseller.market/asp2/pay_wm.asp?id_d=3882685&aff_id=1150998",
      "product_url": "https://www.digiseller.market/product/3882685",
      "currency": "RUB",
      "sales": "0"
    },
    {
      "id": "3820833",
      "name": "Suicide Guy VR",
      "full_name": "РюЁSuicide Guy VRРџАSteam\\лалц+лњлхЛЂЛїлюлИЛђ\\KeyРГљ",
      "price": "49",
      "img": "https://graph.digiseller.ru/img.ashx?id_d=3820833&maxlength=400",
      "buy_url": "https://www.digiseller.market/asp2/pay_wm.asp?id_d=3820833&aff_id=1150998",
      "product_url": "https://www.digiseller.market/product/3820833",
      "currency": "RUB",
      "sales": "0"
    },
    {
      "id": "3923799",
      "name": "Suicide Guy",
      "full_name": "РюЁSuicide Guy: The Lost DreamsРџАSteam\\лалц + люлИЛђ\\KeyРГљ + ­ЪјЂ",
      "price": "39",
      "img": "https://graph.digiseller.ru/img.ashx?id_d=3923799&maxlength=400",
      "buy_url": "https://www.digiseller.market/asp2/pay_wm.asp?id_d=3923799&aff_id=1150998",
      "product_url": "https://www.digiseller.market/product/3923799",
      "currency": "RUB",
      "sales": "0"
    },
    {
      "id": "3971595",
      "name": "Super Bear",
      "full_name": "РюЁSuper Bear: Hunt for the lost beerРџАSteam\\лалц+люлИЛђ\\KeyРГљ",
      "price": "35",
      "img": "https://graph.digiseller.ru/img.ashx?id_d=3971595&maxlength=400",
      "buy_url": "https://www.digiseller.market/asp2/pay_wm.asp?id_d=3971595&aff_id=1150998",
      "product_url": "https://www.digiseller.market/product/3971595",
      "currency": "RUB",
      "sales": "0"
    },
    {
      "id": "3946119",
      "name": "Super Block",
      "full_name": "РюЁSuper Block CrushРџАSteam\\лалц+лњлхЛЂЛїлюлИЛђ\\KeyРГљ",
      "price": "30",
      "img": "https://graph.digiseller.ru/img.ashx?id_d=3946119&maxlength=400",
      "buy_url": "https://www.digiseller.market/asp2/pay_wm.asp?id_d=3946119&aff_id=1150998",
      "product_url": "https://www.digiseller.market/product/3946119",
      "currency": "RUB",
      "sales": "0"
    },
    {
      "id": "3857982",
      "name": "Superbugs",
      "full_name": "РюЁSuperbugs: AwakenРџАSteam\\лалц+лњлхЛЂЛї люлИЛђ\\KeyРГљ + ­ЪјЂлЉлЙлйЛЃЛЂ",
      "price": "160",
      "img": "https://graph.digiseller.ru/img.ashx?id_d=3857982&maxlength=400",
      "buy_url": "https://www.digiseller.market/asp2/pay_wm.asp?id_d=3857982&aff_id=1150998",
      "product_url": "https://www.digiseller.market/product/3857982",
      "currency": "RUB",
      "sales": "0"
    },
    {
      "id": "3961680",
      "name": "Tarantula Vi",
      "full_name": "РюЁTarantula VirusРџАSteam\\лалц + лњлхЛЂЛї люлИЛђ\\KeyРГљ",
      "price": "15",
      "img": "https://graph.digiseller.ru/img.ashx?id_d=3961680&maxlength=400",
      "buy_url": "https://www.digiseller.market/asp2/pay_wm.asp?id_d=3961680&aff_id=1150998",
      "product_url": "https://www.digiseller.market/product/3961680",
      "currency": "RUB",
      "sales": "0"
    },
    {
      "id": "3838231",
      "name": "Terminal squad",
      "full_name": "РюЁTerminal squad: SentinelРџАSteam\\лалц+лњлхЛЂЛїлюлИЛђ\\KeyРГљ",
      "price": "25",
      "img": "https://graph.digiseller.ru/img.ashx?id_d=3838231&maxlength=400",
      "buy_url": "https://www.digiseller.market/asp2/pay_wm.asp?id_d=3838231&aff_id=1150998",
      "product_url": "https://www.digiseller.market/product/3838231",
      "currency": "RUB",
      "sales": "0"
    },
    {
      "id": "3971584",
      "name": "Terminal squad",
      "full_name": "РюЁTerminal squad: SwarmitesРџАSteam\\лалц+лњлхЛЂЛїлюлИЛђ\\KeyРГљ",
      "price": "19",
      "img": "https://graph.digiseller.ru/img.ashx?id_d=3971584&maxlength=400",
      "buy_url": "https://www.digiseller.market/asp2/pay_wm.asp?id_d=3971584&aff_id=1150998",
      "product_url": "https://www.digiseller.market/product/3971584",
      "currency": "RUB",
      "sales": "0"
    },
    {
      "id": "3839399",
      "name": "Teslagrad Remastered Teslagrad Double Pack",
      "full_name": "Teslagrad Remastered & Teslagrad 2 Double Pack лалц+люлИЛђ лџлЏл«лДРГљ + ­ЪјЂлЉлЙлйЛЃЛЂ",
      "price": "149",
      "img": "https://graph.digiseller.ru/img.ashx?id_d=3839399&maxlength=400",
      "buy_url": "https://www.digiseller.market/asp2/pay_wm.asp?id_d=3839399&aff_id=1150998",
      "product_url": "https://www.digiseller.market/product/3839399",
      "currency": "RUB",
      "sales": "0"
    },
    {
      "id": "4425542",
      "name": "TESO Pyromancer's Quandary Emote",
      "full_name": "РюЁTESO Pyromancer's Quandary Emote KeyРџАлџл╗ЛјЛЄРГљ 0%­Ъњ│",
      "price": "45",
      "img": "https://graph.digiseller.ru/img.ashx?id_d=4425542&maxlength=400",
      "buy_url": "https://www.digiseller.market/asp2/pay_wm.asp?id_d=4425542&aff_id=1150998",
      "product_url": "https://www.digiseller.market/product/4425542",
      "currency": "RUB",
      "sales": "0"
    },
    {
      "id": "3795129",
      "name": "The Adventures of Looppy",
      "full_name": "РюЁThe Adventures of LooppyРџАSteam\\лалц+лњлхЛЂЛїлюлИЛђ\\KeyРГљ",
      "price": "50",
      "img": "https://graph.digiseller.ru/img.ashx?id_d=3795129&maxlength=400",
      "buy_url": "https://www.digiseller.market/asp2/pay_wm.asp?id_d=3795129&aff_id=1150998",
      "product_url": "https://www.digiseller.market/product/3795129",
      "currency": "RUB",
      "sales": "0"
    },
    {
      "id": "3777706",
      "name": "The Chant",
      "full_name": "РюЁThe ChantРџАSteam лџлЏл«лД (лалц+лАлЮлЊ) | (Global) | (Tier 1)РГљ+ ­ЪјЂлЉлЙлйЛЃЛЂ",
      "price": "279",
      "img": "https://graph.digiseller.ru/img.ashx?id_d=3777706&maxlength=400",
      "buy_url": "https://www.digiseller.market/asp2/pay_wm.asp?id_d=3777706&aff_id=1150998",
      "product_url": "https://www.digiseller.market/product/3777706",
      "currency": "RUB",
      "sales": "0"
    },
    {
      "id": "3895219",
      "name": "The Chronicles of Nyanya",
      "full_name": "РюЁThe Chronicles of NyanyaРџАSteam\\лалц+лњлхЛЂЛїлюлИЛђ\\KeyРГљ + ­ЪјЂ",
      "price": "120",
      "img": "https://graph.digiseller.ru/img.ashx?id_d=3895219&maxlength=400",
      "buy_url": "https://www.digiseller.market/asp2/pay_wm.asp?id_d=3895219&aff_id=1150998",
      "product_url": "https://www.digiseller.market/product/3895219",
      "currency": "RUB",
      "sales": "0"
    },
    {
      "id": "4019350",
      "name": "The Deed",
      "full_name": "РюЁThe Deed РџА Steam лалц+лАлЮлЊ KeyРГљ + лџл░ЛђЛѓлЙЛЄл║лИ­ЪѓА",
      "price": "20",
      "img": "https://graph.digiseller.ru/img.ashx?id_d=4019350&maxlength=400",
      "buy_url": "https://www.digiseller.market/asp2/pay_wm.asp?id_d=4019350&aff_id=1150998",
      "product_url": "https://www.digiseller.market/product/4019350",
      "currency": "RUB",
      "sales": "0"
    },
    {
      "id": "3839359",
      "name": "The Elder Scrolls IV",
      "full_name": "РюЁThe Elder Scrolls IV: Oblivion GOTY DELUXEРџАSteam Global Key",
      "price": "449",
      "img": "https://graph.digiseller.ru/img.ashx?id_d=3839359&maxlength=400",
      "buy_url": "https://www.digiseller.market/asp2/pay_wm.asp?id_d=3839359&aff_id=1150998",
      "product_url": "https://www.digiseller.market/product/3839359",
      "currency": "RUB",
      "sales": "0"
    },
    {
      "id": "4226614",
      "name": "The Pale Beyond",
      "full_name": "РюЁThe Pale Beyond РџА Steam\\лалц+лњлхЛЂЛїлюлИЛђ\\KeyРГљ + ­ЪјЂлЉлЙлйЛЃЛЂ",
      "price": "85",
      "img": "https://graph.digiseller.ru/img.ashx?id_d=4226614&maxlength=400",
      "buy_url": "https://www.digiseller.market/asp2/pay_wm.asp?id_d=4226614&aff_id=1150998",
      "product_url": "https://www.digiseller.market/product/4226614",
      "currency": "RUB",
      "sales": "0"
    },
    {
      "id": "3861437",
      "name": "The Prison Experiment",
      "full_name": "РюЁThe Prison ExperimentРџАSteam\\лалц+лњлхЛЂЛїлюлИЛђ\\KeyРГљ",
      "price": "99",
      "img": "https://graph.digiseller.ru/img.ashx?id_d=3861437&maxlength=400",
      "buy_url": "https://www.digiseller.market/asp2/pay_wm.asp?id_d=3861437&aff_id=1150998",
      "product_url": "https://www.digiseller.market/product/3861437",
      "currency": "RUB",
      "sales": "0"
    },
    {
      "id": "3820826",
      "name": "Through Abandoned",
      "full_name": "РюЁThrough Abandoned: The ForestРџАSteam\\Global\\KeyРГљCards­ЪѓА",
      "price": "13",
      "img": "https://graph.digiseller.ru/img.ashx?id_d=3820826&maxlength=400",
      "buy_url": "https://www.digiseller.market/asp2/pay_wm.asp?id_d=3820826&aff_id=1150998",
      "product_url": "https://www.digiseller.market/product/3820826",
      "currency": "RUB",
      "sales": "0"
    },
    {
      "id": "3783221",
      "name": "ThrounnelVR",
      "full_name": "РюЁThrounnelVRРџАSteam\\лалц+лњлхЛЂЛї люлИЛђ\\KeyРГљ+ лџл░ЛђЛѓлЙЛЄл║лИ",
      "price": "29",
      "img": "https://graph.digiseller.ru/img.ashx?id_d=3783221&maxlength=400",
      "buy_url": "https://www.digiseller.market/asp2/pay_wm.asp?id_d=3783221&aff_id=1150998",
      "product_url": "https://www.digiseller.market/product/3783221",
      "currency": "RUB",
      "sales": "0"
    },
    {
      "id": "3820836",
      "name": "Train Valley",
      "full_name": "РюЁTrain Valley 2 РџАSteam\\лалц+лњлхЛЂЛїлюлИЛђ\\KeyРГљ + ­ЪјЂлЉлЙлйЛЃЛЂ",
      "price": "30",
      "img": "https://graph.digiseller.ru/img.ashx?id_d=3820836&maxlength=400",
      "buy_url": "https://www.digiseller.market/asp2/pay_wm.asp?id_d=3820836&aff_id=1150998",
      "product_url": "https://www.digiseller.market/product/3820836",
      "currency": "RUB",
      "sales": "0"
    },
    {
      "id": "3938604",
      "name": "Trine",
      "full_name": "Trine 3: The Artifacts of Power РџА Steam лалц+лАлЮлЊ лџлЏл«лДРГљ + ­ЪјЂ лЪлЙл┤л░ЛђлЙл║",
      "price": "105",
      "img": "https://graph.digiseller.ru/img.ashx?id_d=3938604&maxlength=400",
      "buy_url": "https://www.digiseller.market/asp2/pay_wm.asp?id_d=3938604&aff_id=1150998",
      "product_url": "https://www.digiseller.market/product/3938604",
      "currency": "RUB",
      "sales": "0"
    },
    {
      "id": "3789912",
      "name": "Trine",
      "full_name": "Trine 4: The Nightmare Prince РџА Steam лалц+лАлЮлЊ лџлЏл«лДРГљ + ­ЪјЂ лЪлЙл┤л░ЛђлЙл║",
      "price": "215",
      "img": "https://graph.digiseller.ru/img.ashx?id_d=3789912&maxlength=400",
      "buy_url": "https://www.digiseller.market/asp2/pay_wm.asp?id_d=3789912&aff_id=1150998",
      "product_url": "https://www.digiseller.market/product/3789912",
      "currency": "RUB",
      "sales": "0"
    },
    {
      "id": "3783968",
      "name": "Trine Enchanted Edition",
      "full_name": "Trine Enchanted Edition РџА Steam лалц+лАлЮлЊ лџлЏл«лДРГљ + ­ЪјЂ лЪлЙл┤л░ЛђлЙл║",
      "price": "70",
      "img": "https://graph.digiseller.ru/img.ashx?id_d=3783968&maxlength=400",
      "buy_url": "https://www.digiseller.market/asp2/pay_wm.asp?id_d=3783968&aff_id=1150998",
      "product_url": "https://www.digiseller.market/product/3783968",
      "currency": "RUB",
      "sales": "0"
    },
    {
      "id": "4417092",
      "name": "Ultimate Fishing Simulator",
      "full_name": "Ultimate Fishing Simulator РџА Steam лалц+лАлЮлЊ лџлЏл«лДРГљ + ­ЪјЂ лЪлЙл┤л░ЛђлЙл║",
      "price": "199",
      "img": "https://graph.digiseller.ru/img.ashx?id_d=4417092&maxlength=400",
      "buy_url": "https://www.digiseller.market/asp2/pay_wm.asp?id_d=4417092&aff_id=1150998",
      "product_url": "https://www.digiseller.market/product/4417092",
      "currency": "RUB",
      "sales": "0"
    },
    {
      "id": "3861458",
      "name": "Ultimate Soldier",
      "full_name": "РюЁUltimate SoldierРџАSteam\\лалц+лњлхЛЂЛїлюлИЛђ\\KeyРГљ",
      "price": "199",
      "img": "https://graph.digiseller.ru/img.ashx?id_d=3861458&maxlength=400",
      "buy_url": "https://www.digiseller.market/asp2/pay_wm.asp?id_d=3861458&aff_id=1150998",
      "product_url": "https://www.digiseller.market/product/3861458",
      "currency": "RUB",
      "sales": "0"
    },
    {
      "id": "3861510",
      "name": "Unity of Command",
      "full_name": "РюЁUnity of Command: Stalingrad CampaignРџАSteam\\лалц+люлИЛђРГљ",
      "price": "35",
      "img": "https://graph.digiseller.ru/img.ashx?id_d=3861510&maxlength=400",
      "buy_url": "https://www.digiseller.market/asp2/pay_wm.asp?id_d=3861510&aff_id=1150998",
      "product_url": "https://www.digiseller.market/product/3861510",
      "currency": "RUB",
      "sales": "0"
    },
    {
      "id": "3815886",
      "name": "Unsouled",
      "full_name": "РюЁUnsouledРџАSteam\\лалц+лњлхЛЂЛї люлИЛђ\\KeyРГљ + ­ЪјЂ лЉлЙлйЛЃЛЂ",
      "price": "185",
      "img": "https://graph.digiseller.ru/img.ashx?id_d=3815886&maxlength=400",
      "buy_url": "https://www.digiseller.market/asp2/pay_wm.asp?id_d=3815886&aff_id=1150998",
      "product_url": "https://www.digiseller.market/product/3815886",
      "currency": "RUB",
      "sales": "0"
    },
    {
      "id": "3975312",
      "name": "Unstable Portal",
      "full_name": "РюЁUnstable PortalРџАSteam\\лалц+лњлхЛЂЛї люлИЛђ\\KeyРГљ",
      "price": "149",
      "img": "https://graph.digiseller.ru/img.ashx?id_d=3975312&maxlength=400",
      "buy_url": "https://www.digiseller.market/asp2/pay_wm.asp?id_d=3975312&aff_id=1150998",
      "product_url": "https://www.digiseller.market/product/3975312",
      "currency": "RUB",
      "sales": "0"
    },
    {
      "id": "3782779",
      "name": "Unusual Ghost",
      "full_name": "РюЁUnusual GhostРџАSteam\\лалц+лњлхЛЂЛї люлИЛђ\\KeyРГљ",
      "price": "15",
      "img": "https://graph.digiseller.ru/img.ashx?id_d=3782779&maxlength=400",
      "buy_url": "https://www.digiseller.market/asp2/pay_wm.asp?id_d=3782779&aff_id=1150998",
      "product_url": "https://www.digiseller.market/product/3782779",
      "currency": "RUB",
      "sales": "0"
    },
    {
      "id": "5619457",
      "name": "unWorded",
      "full_name": "unWorded РџАSteam лџлЏл«лД лалЙЛЂЛЂлИЛЈ+люлИЛђРГљ",
      "price": "15",
      "img": "https://graph.digiseller.ru/img.ashx?id_d=5619457&maxlength=400",
      "buy_url": "https://www.digiseller.market/asp2/pay_wm.asp?id_d=5619457&aff_id=1150998",
      "product_url": "https://www.digiseller.market/product/5619457",
      "currency": "RUB",
      "sales": "0"
    },
    {
      "id": "3777479",
      "name": "Rising",
      "full_name": "РюЁV Rising РџА Steam лалц+лАлЮлЊ KeyРГљ + ­ЪјЂ лЉлЙлйЛЃЛЂ",
      "price": "525",
      "img": "https://graph.digiseller.ru/img.ashx?id_d=3777479&maxlength=400",
      "buy_url": "https://www.digiseller.market/asp2/pay_wm.asp?id_d=3777479&aff_id=1150998",
      "product_url": "https://www.digiseller.market/product/3777479",
      "currency": "RUB",
      "sales": "0"
    },
    {
      "id": "3783219",
      "name": "War Of Gold Mission 99",
      "full_name": "РюЁWar Of Gold 2 Mission 99РџАSteam\\лалц+лњлхЛЂЛї люлИЛђ\\KeyРГљ",
      "price": "15",
      "img": "https://graph.digiseller.ru/img.ashx?id_d=3783219&maxlength=400",
      "buy_url": "https://www.digiseller.market/asp2/pay_wm.asp?id_d=3783219&aff_id=1150998",
      "product_url": "https://www.digiseller.market/product/3783219",
      "currency": "RUB",
      "sales": "0"
    },
    {
      "id": "4793800",
      "name": "Warframe 13 Year Anniversary Pack Phantasma+Twilight",
      "full_name": "РюЁWarframe 13 Year Anniversary PackРџА Phantasma+TwilightРџА лџл╗ЛјЛЄРГљ",
      "price": "100",
      "img": "https://graph.digiseller.ru/img.ashx?id_d=4793800&maxlength=400",
      "buy_url": "https://www.digiseller.market/asp2/pay_wm.asp?id_d=4793800&aff_id=1150998",
      "product_url": "https://www.digiseller.market/product/4793800",
      "currency": "RUB",
      "sales": "0"
    },
    {
      "id": "3992898",
      "name": "Wizard time!",
      "full_name": "РюЁWizard time!РџАSteam\\лалц+лњлхЛЂЛї люлИЛђ\\KeyРГљ",
      "price": "149",
      "img": "https://graph.digiseller.ru/img.ashx?id_d=3992898&maxlength=400",
      "buy_url": "https://www.digiseller.market/asp2/pay_wm.asp?id_d=3992898&aff_id=1150998",
      "product_url": "https://www.digiseller.market/product/3992898",
      "currency": "RUB",
      "sales": "0"
    },
    {
      "id": "3964520",
      "name": "Wolfenstein II",
      "full_name": "РюЁWolfenstein II: The New Colossus +Deluxe лалц+люлИЛђ\\Key",
      "price": "465",
      "img": "https://graph.digiseller.ru/img.ashx?id_d=3964520&maxlength=400",
      "buy_url": "https://www.digiseller.market/asp2/pay_wm.asp?id_d=3964520&aff_id=1150998",
      "product_url": "https://www.digiseller.market/product/3964520",
      "currency": "RUB",
      "sales": "0"
    },
    {
      "id": "3967410",
      "name": "Woodle Tree",
      "full_name": "РюЁWoodle Tree 2: Deluxe+РџАSteam\\лалц+лњлхЛЂЛїлюлИЛђ\\KeyРГљ",
      "price": "69",
      "img": "https://graph.digiseller.ru/img.ashx?id_d=3967410&maxlength=400",
      "buy_url": "https://www.digiseller.market/asp2/pay_wm.asp?id_d=3967410&aff_id=1150998",
      "product_url": "https://www.digiseller.market/product/3967410",
      "currency": "RUB",
      "sales": "0"
    },
    {
      "id": "3949764",
      "name": "Yummy Girls",
      "full_name": "РюЁYummy Girls 2РџАSteam\\лалц+лњлхЛЂЛї люлИЛђ\\KeyРГљ",
      "price": "50",
      "img": "https://graph.digiseller.ru/img.ashx?id_d=3949764&maxlength=400",
      "buy_url": "https://www.digiseller.market/asp2/pay_wm.asp?id_d=3949764&aff_id=1150998",
      "product_url": "https://www.digiseller.market/product/3949764",
      "currency": "RUB",
      "sales": "0"
    },
    {
      "id": "3961669",
      "name": "жЊХжГѓ№╝џSilver Soul",
      "full_name": "РюЁжЊХжГѓ№╝џSilver SoulРџАSteam\\лалц+лњлхЛЂЛї люлИЛђ\\KeyРГљ",
      "price": "15",
      "img": "https://graph.digiseller.ru/img.ashx?id_d=3961669&maxlength=400",
      "buy_url": "https://www.digiseller.market/asp2/pay_wm.asp?id_d=3961669&aff_id=1150998",
      "product_url": "https://www.digiseller.market/product/3961669",
      "currency": "RUB",
      "sales": "0"
    }
  ],
  "loaded_at": 1777281085.3192654
}